[{"at":"2026-04-10T13:05:11.161Z","cycleMs":1,"ok":true,"mode":"5m","signalsCount":0,"cycleProfileMs":{}},{"at":"2026-04-10T13:05:12.182Z","cycleMs":1,"ok":true,"mode":"5m","signalsCount":0,"cycleProfileMs":{}},{"at":"2026-04-10T13:05:12.196Z","cycleMs":1,"ok":true,"mode":"5m","signalsCount":0,"cycleProfileMs":{}},{"at":"2026-04-10T13:05:13.211Z","cycleMs":1,"ok":true,"mode":"5m","signalsCount":0,"cycleProfileMs":{}},{"at":"2026-04-10T13:05:20.335Z","cycleMs":1,"ok":true,"mode":"5m","signalsCount":0,"cycleProfileMs":{}},{"at":"2026-04-10T13:05:22.386Z","cycleMs":1,"ok":true,"mode":"5m","signalsCount":0,"cycleProfileMs":{}},{"at":"2026-04-10T13:05:24.438Z","cycleMs":1,"ok":true,"mode":"5m","signalsCount":0,"cycleProfileMs":{}},{"at":"2026-04-10T13:05:25.463Z","cycleMs":1,"ok":true,"mode":"5m","signalsCount":0,"cycleProfileMs":{}},{"at":"2026-04-10T13:05:27.495Z","cycleMs":1,"ok":true,"mode":"5m","signalsCount":0,"cycleProfileMs":{}},{"at":"2026-04-10T13:05:28.524Z","cycleMs":1,"ok":true,"mode":"5m","signalsCount":0,"cycleProfileMs":{}},{"at":"2026-04-10T13:05:30.570Z","cycleMs":1,"ok":true,"mode":"5m","signalsCount":0,"cycleProfileMs":{}},{"at":"2026-04-10T13:05:31.594Z","cycleMs":1,"ok":true,"mode":"5m","signalsCount":0,"cycleProfileMs":{}},{"at":"2026-04-10T13:05:42.825Z","cycleMs":1,"ok":true,"mode":"5m","signalsCount":0,"cycleProfileMs":{}},{"at":"2026-04-10T13:05:44.876Z","cycleMs":1,"ok":true,"mode":"5m","signalsCount":0,"cycleProfileMs":{}},{"at":"2026-04-10T13:05:44.877Z","cycleMs":1,"ok":true,"mode":"5m","signalsCount":0,"cycleProfileMs":{}},{"at":"2026-04-10T13:05:48.970Z","cycleMs":1,"ok":true,"mode":"5m","signalsCount":0,"cycleProfileMs":{}},{"at":"2026-04-10T13:05:52.024Z","cycleMs":1,"ok":true,"mode":"5m","signalsCount":0,"cycleProfileMs":{}},{"at":"2026-04-10T13:05:52.038Z","cycleMs":1,"ok":true,"mode":"5m","signalsCount":0,"cycleProfileMs":{}},{"at":"2026-04-10T13:05:53.053Z","cycleMs":1,"ok":true,"mode":"5m","signalsCount":0,"cycleProfileMs":{}},{"at":"2026-04-10T13:05:54.075Z","cycleMs":1,"ok":true,"mode":"5m","signalsCount":0,"cycleProfileMs":{}},{"at":"2026-04-10T13:05:59.207Z","cycleMs":1,"ok":true,"mode":"5m","signalsCount":0,"cycleProfileMs":{}},{"at":"2026-04-10T13:06:00.221Z","cycleMs":1,"ok":true,"mode":"5m","signalsCount":0,"cycleProfileMs":{}},{"at":"2026-04-10T13:06:04.301Z","cycleMs":1,"ok":true,"mode":"5m","signalsCount":0,"cycleProfileMs":{}},{"at":"2026-04-10T13:06:04.312Z","cycleMs":1,"ok":true,"mode":"5m","signalsCount":0,"cycleProfileMs":{}},{"at":"2026-04-10T13:06:07.370Z","cycleMs":1,"ok":true,"mode":"5m","signalsCount":0,"cycleProfileMs":{}},{"at":"2026-04-10T13:06:14.537Z","cycleMs":1,"ok":true,"mode":"5m","signalsCount":0,"cycleProfileMs":{}},{"at":"2026-04-10T13:06:15.552Z","cycleMs":1,"ok":true,"mode":"5m","signalsCount":0,"cycleProfileMs":{}},{"at":"2026-04-10T13:06:16.574Z","cycleMs":1,"ok":true,"mode":"5m","signalsCount":0,"cycleProfileMs":{}},{"at":"2026-04-10T13:06:17.611Z","cycleMs":1,"ok":true,"mode":"5m","signalsCount":0,"cycleProfileMs":{}},{"at":"2026-04-10T13:06:18.607Z","cycleMs":1,"ok":true,"mode":"5m","signalsCount":0,"cycleProfileMs":{}},{"at":"2026-04-10T13:06:21.680Z","cycleMs":1,"ok":true,"mode":"5m","signalsCount":0,"cycleProfileMs":{}},{"at":"2026-04-10T13:06:21.694Z","cycleMs":1,"ok":true,"mode":"5m","signalsCount":0,"cycleProfileMs":{}},{"at":"2026-04-10T13:06:22.706Z","cycleMs":1,"ok":true,"mode":"5m","signalsCount":0,"cycleProfileMs":{}},{"at":"2026-04-10T13:06:23.726Z","cycleMs":1,"ok":true,"mode":"5m","signalsCount":0,"cycleProfileMs":{}},{"at":"2026-04-10T13:06:24.751Z","cycleMs":1,"ok":true,"mode":"5m","signalsCount":0,"cycleProfileMs":{}},{"at":"2026-04-10T13:06:25.769Z","cycleMs":1,"ok":true,"mode":"5m","signalsCount":0,"cycleProfileMs":{}},{"at":"2026-04-10T13:06:26.794Z","cycleMs":1,"ok":true,"mode":"5m","signalsCount":0,"cycleProfileMs":{}},{"at":"2026-04-10T13:06:28.841Z","cycleMs":1,"ok":true,"mode":"5m","signalsCount":0,"cycleProfileMs":{}},{"at":"2026-04-10T13:06:31.917Z","cycleMs":1,"ok":true,"mode":"5m","signalsCount":0,"cycleProfileMs":{}},{"at":"2026-04-10T13:06:33.962Z","cycleMs":1,"ok":true,"mode":"5m","signalsCount":0,"cycleProfileMs":{}},{"at":"2026-04-10T13:06:35.993Z","cycleMs":1,"ok":true,"mode":"5m","signalsCount":0,"cycleProfileMs":{}},{"at":"2026-04-10T13:06:38.042Z","cycleMs":1,"ok":true,"mode":"5m","signalsCount":0,"cycleProfileMs":{}},{"at":"2026-04-10T13:06:39.065Z","cycleMs":1,"ok":true,"mode":"5m","signalsCount":0,"cycleProfileMs":{}},{"at":"2026-04-10T13:06:39.080Z","cycleMs":1,"ok":true,"mode":"5m","signalsCount":0,"cycleProfileMs":{}},{"at":"2026-04-10T13:06:40.097Z","cycleMs":1,"ok":true,"mode":"5m","signalsCount":0,"cycleProfileMs":{}},{"at":"2026-04-10T13:06:42.163Z","cycleMs":1,"ok":true,"mode":"5m","signalsCount":0,"cycleProfileMs":{}},{"at":"2026-04-10T13:06:43.198Z","cycleMs":1,"ok":true,"mode":"5m","signalsCount":0,"cycleProfileMs":{}},{"at":"2026-04-10T13:06:45.232Z","cycleMs":1,"ok":true,"mode":"5m","signalsCount":0,"cycleProfileMs":{}},{"at":"2026-04-10T13:06:48.291Z","cycleMs":1,"ok":true,"mode":"5m","signalsCount":0,"cycleProfileMs":{}},{"at":"2026-04-10T13:06:49.326Z","cycleMs":1,"ok":true,"mode":"5m","signalsCount":0,"cycleProfileMs":{}},{"at":"2026-04-10T13:06:50.360Z","cycleMs":1,"ok":true,"mode":"5m","signalsCount":0,"cycleProfileMs":{}},{"at":"2026-04-10T13:06:52.394Z","cycleMs":1,"ok":true,"mode":"5m","signalsCount":0,"cycleProfileMs":{}},{"at":"2026-04-10T13:06:53.413Z","cycleMs":1,"ok":true,"mode":"5m","signalsCount":0,"cycleProfileMs":{}},{"at":"2026-04-10T13:06:55.476Z","cycleMs":1,"ok":true,"mode":"5m","signalsCount":0,"cycleProfileMs":{}},{"at":"2026-04-10T13:06:56.489Z","cycleMs":1,"ok":true,"mode":"5m","signalsCount":0,"cycleProfileMs":{}},{"at":"2026-04-10T13:06:57.524Z","cycleMs":1,"ok":true,"mode":"5m","signalsCount":0,"cycleProfileMs":{}},{"at":"2026-04-10T13:07:01.593Z","cycleMs":1,"ok":true,"mode":"5m","signalsCount":0,"cycleProfileMs":{}},{"at":"2026-04-10T13:07:02.619Z","cycleMs":1,"ok":true,"mode":"5m","signalsCount":0,"cycleProfileMs":{}},{"at":"2026-04-10T13:07:04.671Z","cycleMs":1,"ok":true,"mode":"5m","signalsCount":0,"cycleProfileMs":{}},{"at":"2026-04-10T13:07:05.684Z","cycleMs":1,"ok":true,"mode":"5m","signalsCount":0,"cycleProfileMs":{}},{"at":"2026-04-10T13:07:10.794Z","cycleMs":1,"ok":true,"mode":"5m","signalsCount":0,"cycleProfileMs":{}},{"at":"2026-04-10T13:07:11.820Z","cycleMs":1,"ok":true,"mode":"5m","signalsCount":0,"cycleProfileMs":{}},{"at":"2026-04-10T13:07:13.857Z","cycleMs":1,"ok":true,"mode":"5m","signalsCount":0,"cycleProfileMs":{}},{"at":"2026-04-10T13:07:13.869Z","cycleMs":1,"ok":true,"mode":"5m","signalsCount":0,"cycleProfileMs":{}},{"at":"2026-04-10T13:07:14.877Z","cycleMs":1,"ok":true,"mode":"5m","signalsCount":0,"cycleProfileMs":{}},{"at":"2026-04-10T13:07:15.905Z","cycleMs":1,"ok":true,"mode":"5m","signalsCount":0,"cycleProfileMs":{}},{"at":"2026-04-10T13:07:17.941Z","cycleMs":1,"ok":true,"mode":"5m","signalsCount":0,"cycleProfileMs":{}},{"at":"2026-04-10T13:07:21.012Z","cycleMs":1,"ok":true,"mode":"5m","signalsCount":0,"cycleProfileMs":{}},{"at":"2026-04-10T13:07:22.027Z","cycleMs":1,"ok":true,"mode":"5m","signalsCount":0,"cycleProfileMs":{}},{"at":"2026-04-10T13:07:22.039Z","cycleMs":1,"ok":true,"mode":"5m","signalsCount":0,"cycleProfileMs":{}},{"at":"2026-04-10T13:07:27.136Z","cycleMs":1,"ok":true,"mode":"5m","signalsCount":0,"cycleProfileMs":{}},{"at":"2026-04-10T13:07:27.152Z","cycleMs":1,"ok":true,"mode":"5m","signalsCount":0,"cycleProfileMs":{}},{"at":"2026-04-10T13:07:30.190Z","cycleMs":1,"ok":true,"mode":"5m","signalsCount":0,"cycleProfileMs":{}},{"at":"2026-04-10T13:07:30.210Z","cycleMs":1,"ok":true,"mode":"5m","signalsCount":0,"cycleProfileMs":{}},{"at":"2026-04-10T13:07:32.230Z","cycleMs":1,"ok":true,"mode":"5m","signalsCount":0,"cycleProfileMs":{}},{"at":"2026-04-10T13:07:32.245Z","cycleMs":1,"ok":true,"mode":"5m","signalsCount":0,"cycleProfileMs":{}},{"at":"2026-04-10T13:07:33.241Z","cycleMs":1,"ok":true,"mode":"5m","signalsCount":0,"cycleProfileMs":{}},{"at":"2026-04-10T13:07:33.259Z","cycleMs":1,"ok":true,"mode":"5m","signalsCount":0,"cycleProfileMs":{}},{"at":"2026-04-10T13:07:34.287Z","cycleMs":1,"ok":true,"mode":"5m","signalsCount":0,"cycleProfileMs":{}},{"at":"2026-04-10T13:07:35.310Z","cycleMs":1,"ok":true,"mode":"5m","signalsCount":0,"cycleProfileMs":{}},{"at":"2026-04-10T13:07:37.348Z","cycleMs":1,"ok":true,"mode":"5m","signalsCount":0,"cycleProfileMs":{}},{"at":"2026-04-10T13:07:39.394Z","cycleMs":1,"ok":true,"mode":"5m","signalsCount":0,"cycleProfileMs":{}},{"at":"2026-04-10T13:07:42.461Z","cycleMs":1,"ok":true,"mode":"5m","signalsCount":0,"cycleProfileMs":{}},{"at":"2026-04-10T13:07:44.528Z","cycleMs":1,"ok":true,"mode":"5m","signalsCount":0,"cycleProfileMs":{}},{"at":"2026-04-10T13:07:48.613Z","cycleMs":1,"ok":true,"mode":"5m","signalsCount":0,"cycleProfileMs":{}},{"at":"2026-04-10T13:07:50.606Z","cycleMs":1,"ok":true,"mode":"5m","signalsCount":0,"cycleProfileMs":{}},{"at":"2026-04-10T13:07:52.648Z","cycleMs":1,"ok":true,"mode":"5m","signalsCount":0,"cycleProfileMs":{}},{"at":"2026-04-10T13:07:52.694Z","cycleMs":1,"ok":true,"mode":"5m","signalsCount":0,"cycleProfileMs":{}},{"at":"2026-04-10T13:07:53.710Z","cycleMs":1,"ok":true,"mode":"5m","signalsCount":0,"cycleProfileMs":{}},{"at":"2026-04-10T13:07:55.761Z","cycleMs":1,"ok":true,"mode":"5m","signalsCount":0,"cycleProfileMs":{}},{"at":"2026-04-10T13:07:58.829Z","cycleMs":1,"ok":true,"mode":"5m","signalsCount":0,"cycleProfileMs":{}},{"at":"2026-04-10T13:07:59.781Z","cycleMs":1,"ok":true,"mode":"5m","signalsCount":0,"cycleProfileMs":{}},{"at":"2026-04-10T13:08:00.808Z","cycleMs":1,"ok":true,"mode":"5m","signalsCount":0,"cycleProfileMs":{}},{"at":"2026-04-10T13:08:02.925Z","cycleMs":1,"ok":true,"mode":"5m","signalsCount":0,"cycleProfileMs":{}},{"at":"2026-04-10T13:08:05.993Z","cycleMs":1,"ok":true,"mode":"5m","signalsCount":0,"cycleProfileMs":{}},{"at":"2026-04-10T13:08:08.959Z","cycleMs":1,"ok":true,"mode":"5m","signalsCount":0,"cycleProfileMs":{}},{"at":"2026-04-10T13:08:10.999Z","cycleMs":1,"ok":true,"mode":"5m","signalsCount":0,"cycleProfileMs":{}},{"at":"2026-04-10T13:08:12.045Z","cycleMs":1,"ok":true,"mode":"5m","signalsCount":0,"cycleProfileMs":{}},{"at":"2026-04-10T13:08:13.148Z","cycleMs":1,"ok":true,"mode":"5m","signalsCount":0,"cycleProfileMs":{}},{"at":"2026-04-10T13:08:16.202Z","cycleMs":1,"ok":true,"mode":"5m","signalsCount":0,"cycleProfileMs":{}},{"at":"2026-04-10T13:08:17.228Z","cycleMs":1,"ok":true,"mode":"5m","signalsCount":0,"cycleProfileMs":{}},{"at":"2026-04-10T13:08:18.224Z","cycleMs":1,"ok":true,"mode":"5m","signalsCount":0,"cycleProfileMs":{}},{"at":"2026-04-10T13:08:19.287Z","cycleMs":1,"ok":true,"mode":"5m","signalsCount":0,"cycleProfileMs":{}},{"at":"2026-04-10T13:08:20.265Z","cycleMs":1,"ok":true,"mode":"5m","signalsCount":0,"cycleProfileMs":{}},{"at":"2026-04-10T13:08:21.295Z","cycleMs":1,"ok":true,"mode":"5m","signalsCount":0,"cycleProfileMs":{}},{"at":"2026-04-10T13:08:22.322Z","cycleMs":1,"ok":true,"mode":"5m","signalsCount":0,"cycleProfileMs":{}},{"at":"2026-04-10T13:08:22.348Z","cycleMs":1,"ok":true,"mode":"5m","signalsCount":0,"cycleProfileMs":{}},{"at":"2026-04-10T13:08:23.348Z","cycleMs":1,"ok":true,"mode":"5m","signalsCount":0,"cycleProfileMs":{}},{"at":"2026-04-10T13:08:24.377Z","cycleMs":1,"ok":true,"mode":"5m","signalsCount":0,"cycleProfileMs":{}},{"at":"2026-04-10T13:08:26.436Z","cycleMs":1,"ok":true,"mode":"5m","signalsCount":0,"cycleProfileMs":{}},{"at":"2026-04-10T13:08:28.470Z","cycleMs":1,"ok":true,"mode":"5m","signalsCount":0,"cycleProfileMs":{}},{"at":"2026-04-10T13:08:29.526Z","cycleMs":1,"ok":true,"mode":"5m","signalsCount":0,"cycleProfileMs":{}},{"at":"2026-04-10T13:08:30.510Z","cycleMs":1,"ok":true,"mode":"5m","signalsCount":0,"cycleProfileMs":{}},{"at":"2026-04-10T13:08:32.587Z","cycleMs":1,"ok":true,"mode":"5m","signalsCount":0,"cycleProfileMs":{}},{"at":"2026-04-10T13:08:33.579Z","cycleMs":1,"ok":true,"mode":"5m","signalsCount":0,"cycleProfileMs":{}},{"at":"2026-04-10T13:08:34.621Z","cycleMs":1,"ok":true,"mode":"5m","signalsCount":0,"cycleProfileMs":{}},{"at":"2026-04-10T13:08:35.639Z","cycleMs":1,"ok":true,"mode":"5m","signalsCount":0,"cycleProfileMs":{}},{"at":"2026-04-10T13:08:36.657Z","cycleMs":1,"ok":true,"mode":"5m","signalsCount":0,"cycleProfileMs":{}},{"at":"2026-04-10T13:08:37.654Z","cycleMs":1,"ok":true,"mode":"5m","signalsCount":0,"cycleProfileMs":{}},{"at":"2026-04-10T13:08:38.679Z","cycleMs":1,"ok":true,"mode":"5m","signalsCount":0,"cycleProfileMs":{}},{"at":"2026-04-10T13:08:41.727Z","cycleMs":1,"ok":true,"mode":"5m","signalsCount":0,"cycleProfileMs":{}},{"at":"2026-04-10T13:08:41.756Z","cycleMs":1,"ok":true,"mode":"5m","signalsCount":0,"cycleProfileMs":{}},{"at":"2026-04-10T13:08:43.771Z","cycleMs":1,"ok":true,"mode":"5m","signalsCount":0,"cycleProfileMs":{}},{"at":"2026-04-10T13:08:48.885Z","cycleMs":1,"ok":true,"mode":"5m","signalsCount":0,"cycleProfileMs":{}},{"at":"2026-04-10T13:08:50.924Z","cycleMs":1,"ok":true,"mode":"5m","signalsCount":0,"cycleProfileMs":{}},{"at":"2026-04-10T13:08:52.982Z","cycleMs":1,"ok":true,"mode":"5m","signalsCount":0,"cycleProfileMs":{}},{"at":"2026-04-10T13:08:54.008Z","cycleMs":1,"ok":true,"mode":"5m","signalsCount":0,"cycleProfileMs":{}},{"at":"2026-04-10T13:08:57.056Z","cycleMs":1,"ok":true,"mode":"5m","signalsCount":0,"cycleProfileMs":{}},{"at":"2026-04-10T13:08:58.073Z","cycleMs":1,"ok":true,"mode":"5m","signalsCount":0,"cycleProfileMs":{}},{"at":"2026-04-10T13:08:59.084Z","cycleMs":1,"ok":true,"mode":"5m","signalsCount":0,"cycleProfileMs":{}},{"at":"2026-04-10T13:09:01.129Z","cycleMs":1,"ok":true,"mode":"5m","signalsCount":0,"cycleProfileMs":{}},{"at":"2026-04-10T13:09:02.154Z","cycleMs":1,"ok":true,"mode":"5m","signalsCount":0,"cycleProfileMs":{}},{"at":"2026-04-10T13:09:04.196Z","cycleMs":1,"ok":true,"mode":"5m","signalsCount":0,"cycleProfileMs":{}},{"at":"2026-04-10T13:09:04.212Z","cycleMs":1,"ok":true,"mode":"5m","signalsCount":0,"cycleProfileMs":{}},{"at":"2026-04-10T13:09:05.234Z","cycleMs":1,"ok":true,"mode":"5m","signalsCount":0,"cycleProfileMs":{}},{"at":"2026-04-10T13:09:07.246Z","cycleMs":1,"ok":true,"mode":"5m","signalsCount":0,"cycleProfileMs":{}},{"at":"2026-04-10T13:09:08.259Z","cycleMs":1,"ok":true,"mode":"5m","signalsCount":0,"cycleProfileMs":{}},{"at":"2026-04-10T13:09:09.284Z","cycleMs":1,"ok":true,"mode":"5m","signalsCount":0,"cycleProfileMs":{}},{"at":"2026-04-10T13:09:12.364Z","cycleMs":1,"ok":true,"mode":"5m","signalsCount":0,"cycleProfileMs":{}},{"at":"2026-04-10T13:09:13.387Z","cycleMs":1,"ok":true,"mode":"5m","signalsCount":0,"cycleProfileMs":{}},{"at":"2026-04-10T13:09:15.433Z","cycleMs":1,"ok":true,"mode":"5m","signalsCount":0,"cycleProfileMs":{}},{"at":"2026-04-10T13:09:18.505Z","cycleMs":1,"ok":true,"mode":"5m","signalsCount":0,"cycleProfileMs":{}},{"at":"2026-04-10T13:09:19.511Z","cycleMs":1,"ok":true,"mode":"5m","signalsCount":0,"cycleProfileMs":{}},{"at":"2026-04-10T13:09:19.525Z","cycleMs":1,"ok":true,"mode":"5m","signalsCount":0,"cycleProfileMs":{}},{"at":"2026-04-10T13:09:20.552Z","cycleMs":1,"ok":true,"mode":"5m","signalsCount":0,"cycleProfileMs":{}},{"at":"2026-04-10T13:09:23.611Z","cycleMs":1,"ok":true,"mode":"5m","signalsCount":0,"cycleProfileMs":{}},{"at":"2026-04-10T13:09:27.688Z","cycleMs":1,"ok":true,"mode":"5m","signalsCount":0,"cycleProfileMs":{}},{"at":"2026-04-10T13:09:30.740Z","cycleMs":1,"ok":true,"mode":"5m","signalsCount":0,"cycleProfileMs":{}},{"at":"2026-04-10T13:09:32.790Z","cycleMs":1,"ok":true,"mode":"5m","signalsCount":0,"cycleProfileMs":{}},{"at":"2026-04-10T13:09:33.814Z","cycleMs":1,"ok":true,"mode":"5m","signalsCount":0,"cycleProfileMs":{}},{"at":"2026-04-10T13:09:34.841Z","cycleMs":1,"ok":true,"mode":"5m","signalsCount":0,"cycleProfileMs":{}},{"at":"2026-04-10T13:09:36.889Z","cycleMs":1,"ok":true,"mode":"5m","signalsCount":0,"cycleProfileMs":{}},{"at":"2026-04-10T13:09:36.915Z","cycleMs":1,"ok":true,"mode":"5m","signalsCount":0,"cycleProfileMs":{}},{"at":"2026-04-10T13:09:37.910Z","cycleMs":1,"ok":true,"mode":"5m","signalsCount":0,"cycleProfileMs":{}},{"at":"2026-04-10T13:09:38.930Z","cycleMs":1,"ok":true,"mode":"5m","signalsCount":0,"cycleProfileMs":{}},{"at":"2026-04-10T13:09:44.073Z","cycleMs":1,"ok":true,"mode":"5m","signalsCount":0,"cycleProfileMs":{}},{"at":"2026-04-10T13:09:45.098Z","cycleMs":1,"ok":true,"mode":"5m","signalsCount":0,"cycleProfileMs":{}},{"at":"2026-04-10T13:09:46.086Z","cycleMs":1,"ok":true,"mode":"5m","signalsCount":0,"cycleProfileMs":{}},{"at":"2026-04-10T13:09:46.113Z","cycleMs":1,"ok":true,"mode":"5m","signalsCount":0,"cycleProfileMs":{}},{"at":"2026-04-10T13:09:47.142Z","cycleMs":1,"ok":true,"mode":"5m","signalsCount":0,"cycleProfileMs":{}},{"at":"2026-04-10T13:09:49.189Z","cycleMs":1,"ok":true,"mode":"5m","signalsCount":0,"cycleProfileMs":{}},{"at":"2026-04-10T13:09:52.217Z","cycleMs":1,"ok":true,"mode":"5m","signalsCount":0,"cycleProfileMs":{}},{"at":"2026-04-10T13:09:53.245Z","cycleMs":1,"ok":true,"mode":"5m","signalsCount":0,"cycleProfileMs":{}},{"at":"2026-04-10T13:09:55.290Z","cycleMs":1,"ok":true,"mode":"5m","signalsCount":0,"cycleProfileMs":{}},{"at":"2026-04-10T13:09:56.322Z","cycleMs":1,"ok":true,"mode":"5m","signalsCount":0,"cycleProfileMs":{}},{"at":"2026-04-10T13:09:57.344Z","cycleMs":1,"ok":true,"mode":"5m","signalsCount":0,"cycleProfileMs":{}},{"at":"2026-04-10T13:09:58.386Z","cycleMs":1,"ok":true,"mode":"5m","signalsCount":0,"cycleProfileMs":{}},{"at":"2026-04-10T13:09:59.407Z","cycleMs":1,"ok":true,"mode":"5m","signalsCount":0,"cycleProfileMs":{}},{"at":"2026-04-10T13:10:03.467Z","cycleMs":1,"ok":true,"mode":"5m","signalsCount":0,"cycleProfileMs":{}},{"at":"2026-04-10T13:10:04.496Z","cycleMs":1,"ok":true,"mode":"5m","signalsCount":0,"cycleProfileMs":{}},{"at":"2026-04-10T13:10:05.530Z","cycleMs":1,"ok":true,"mode":"5m","signalsCount":0,"cycleProfileMs":{}},{"at":"2026-04-10T13:10:06.548Z","cycleMs":1,"ok":true,"mode":"5m","signalsCount":0,"cycleProfileMs":{}},{"at":"2026-04-10T13:10:07.571Z","cycleMs":1,"ok":true,"mode":"5m","signalsCount":0,"cycleProfileMs":{}},{"at":"2026-04-10T13:10:07.578Z","cycleMs":1,"ok":true,"mode":"5m","signalsCount":0,"cycleProfileMs":{}},{"at":"2026-04-10T13:10:09.624Z","cycleMs":1,"ok":true,"mode":"5m","signalsCount":0,"cycleProfileMs":{}},{"at":"2026-04-10T13:10:11.679Z","cycleMs":1,"ok":true,"mode":"5m","signalsCount":0,"cycleProfileMs":{}},{"at":"2026-04-10T13:10:12.692Z","cycleMs":1,"ok":true,"mode":"5m","signalsCount":0,"cycleProfileMs":{}},{"at":"2026-04-10T13:10:13.721Z","cycleMs":1,"ok":true,"mode":"5m","signalsCount":0,"cycleProfileMs":{}},{"at":"2026-04-10T13:10:15.776Z","cycleMs":1,"ok":true,"mode":"5m","signalsCount":0,"cycleProfileMs":{}},{"at":"2026-04-10T13:10:16.796Z","cycleMs":1,"ok":true,"mode":"5m","signalsCount":0,"cycleProfileMs":{}},{"at":"2026-04-10T13:10:17.814Z","cycleMs":1,"ok":true,"mode":"5m","signalsCount":0,"cycleProfileMs":{}},{"at":"2026-04-10T13:10:17.834Z","cycleMs":1,"ok":true,"mode":"5m","signalsCount":0,"cycleProfileMs":{}},{"at":"2026-04-10T13:10:19.860Z","cycleMs":1,"ok":true,"mode":"5m","signalsCount":0,"cycleProfileMs":{}},{"at":"2026-04-10T13:10:20.891Z","cycleMs":1,"ok":true,"mode":"5m","signalsCount":0,"cycleProfileMs":{}},{"at":"2026-04-10T13:10:21.918Z","cycleMs":1,"ok":true,"mode":"5m","signalsCount":0,"cycleProfileMs":{}},{"at":"2026-04-10T13:10:25.004Z","cycleMs":1,"ok":true,"mode":"5m","signalsCount":0,"cycleProfileMs":{}},{"at":"2026-04-10T13:10:26.035Z","cycleMs":1,"ok":true,"mode":"5m","signalsCount":0,"cycleProfileMs":{}},{"at":"2026-04-10T13:10:27.058Z","cycleMs":1,"ok":true,"mode":"5m","signalsCount":0,"cycleProfileMs":{}},{"at":"2026-04-10T13:10:28.081Z","cycleMs":1,"ok":true,"mode":"5m","signalsCount":0,"cycleProfileMs":{}},{"at":"2026-04-10T13:10:29.095Z","cycleMs":1,"ok":true,"mode":"5m","signalsCount":0,"cycleProfileMs":{}},{"at":"2026-04-10T13:10:32.180Z","cycleMs":1,"ok":true,"mode":"5m","signalsCount":0,"cycleProfileMs":{}},{"at":"2026-04-10T13:10:33.212Z","cycleMs":1,"ok":true,"mode":"5m","signalsCount":0,"cycleProfileMs":{}},{"at":"2026-04-10T13:10:34.232Z","cycleMs":1,"ok":true,"mode":"5m","signalsCount":0,"cycleProfileMs":{}},{"at":"2026-04-10T13:10:35.265Z","cycleMs":1,"ok":true,"mode":"5m","signalsCount":0,"cycleProfileMs":{}},{"at":"2026-04-10T13:10:37.320Z","cycleMs":1,"ok":true,"mode":"5m","signalsCount":0,"cycleProfileMs":{}},{"at":"2026-04-10T13:10:37.324Z","cycleMs":1,"ok":true,"mode":"5m","signalsCount":0,"cycleProfileMs":{}},{"at":"2026-04-10T13:10:40.407Z","cycleMs":1,"ok":true,"mode":"5m","signalsCount":0,"cycleProfileMs":{}},{"at":"2026-04-10T13:10:41.430Z","cycleMs":1,"ok":true,"mode":"5m","signalsCount":0,"cycleProfileMs":{}},{"at":"2026-04-10T13:10:41.435Z","cycleMs":1,"ok":true,"mode":"5m","signalsCount":0,"cycleProfileMs":{}},{"at":"2026-04-10T13:10:42.458Z","cycleMs":1,"ok":true,"mode":"5m","signalsCount":0,"cycleProfileMs":{}},{"at":"2026-04-10T13:10:43.483Z","cycleMs":1,"ok":true,"mode":"5m","signalsCount":0,"cycleProfileMs":{}},{"at":"2026-04-10T13:10:44.511Z","cycleMs":1,"ok":true,"mode":"5m","signalsCount":0,"cycleProfileMs":{}},{"at":"2026-04-10T13:10:45.542Z","cycleMs":1,"ok":true,"mode":"5m","signalsCount":0,"cycleProfileMs":{}},{"at":"2026-04-10T13:10:46.573Z","cycleMs":1,"ok":true,"mode":"5m","signalsCount":0,"cycleProfileMs":{}},{"at":"2026-04-10T13:10:47.586Z","cycleMs":1,"ok":true,"mode":"5m","signalsCount":0,"cycleProfileMs":{}},{"at":"2026-04-10T13:10:47.600Z","cycleMs":1,"ok":true,"mode":"5m","signalsCount":0,"cycleProfileMs":{}},{"at":"2026-04-10T13:10:49.628Z","cycleMs":1,"ok":true,"mode":"5m","signalsCount":0,"cycleProfileMs":{}},{"at":"2026-04-10T13:10:52.682Z","cycleMs":1,"ok":true,"mode":"5m","signalsCount":0,"cycleProfileMs":{}},{"at":"2026-04-10T13:10:53.696Z","cycleMs":1,"ok":true,"mode":"5m","signalsCount":0,"cycleProfileMs":{}},{"at":"2026-04-10T13:10:55.728Z","cycleMs":1,"ok":true,"mode":"5m","signalsCount":0,"cycleProfileMs":{}},{"at":"2026-04-10T13:10:56.753Z","cycleMs":1,"ok":true,"mode":"5m","signalsCount":0,"cycleProfileMs":{}},{"at":"2026-04-10T13:10:57.777Z","cycleMs":2,"ok":true,"mode":"5m","signalsCount":0,"cycleProfileMs":{}},{"at":"2026-04-10T13:11:01.844Z","cycleMs":1,"ok":true,"mode":"5m","signalsCount":0,"cycleProfileMs":{}},{"at":"2026-04-10T13:11:03.871Z","cycleMs":1,"ok":true,"mode":"5m","signalsCount":0,"cycleProfileMs":{}},{"at":"2026-04-10T13:11:07.936Z","cycleMs":1,"ok":true,"mode":"5m","signalsCount":0,"cycleProfileMs":{}},{"at":"2026-04-10T13:11:08.949Z","cycleMs":1,"ok":true,"mode":"5m","signalsCount":0,"cycleProfileMs":{}},{"at":"2026-04-10T13:11:11.990Z","cycleMs":1,"ok":true,"mode":"5m","signalsCount":0,"cycleProfileMs":{}},{"at":"2026-04-10T13:11:14.017Z","cycleMs":3,"ok":true,"mode":"5m","signalsCount":0,"cycleProfileMs":{}},{"at":"2026-04-10T13:11:16.071Z","cycleMs":1,"ok":true,"mode":"5m","signalsCount":0,"cycleProfileMs":{}},{"at":"2026-04-10T13:11:17.100Z","cycleMs":1,"ok":true,"mode":"5m","signalsCount":0,"cycleProfileMs":{}},{"at":"2026-04-10T13:11:20.152Z","cycleMs":2,"ok":true,"mode":"5m","signalsCount":0,"cycleProfileMs":{}},{"at":"2026-04-10T13:11:22.190Z","cycleMs":1,"ok":true,"mode":"5m","signalsCount":0,"cycleProfileMs":{}},{"at":"2026-04-10T13:11:24.221Z","cycleMs":1,"ok":true,"mode":"5m","signalsCount":0,"cycleProfileMs":{}},{"at":"2026-04-10T13:11:26.267Z","cycleMs":1,"ok":true,"mode":"5m","signalsCount":0,"cycleProfileMs":{}},{"at":"2026-04-10T13:11:27.288Z","cycleMs":1,"ok":true,"mode":"5m","signalsCount":0,"cycleProfileMs":{}},{"at":"2026-04-10T13:11:28.315Z","cycleMs":1,"ok":true,"mode":"5m","signalsCount":0,"cycleProfileMs":{}},{"at":"2026-04-10T13:11:29.341Z","cycleMs":1,"ok":true,"mode":"5m","signalsCount":0,"cycleProfileMs":{}},{"at":"2026-04-10T13:11:32.395Z","cycleMs":1,"ok":true,"mode":"5m","signalsCount":0,"cycleProfileMs":{}},{"at":"2026-04-10T13:11:33.415Z","cycleMs":1,"ok":true,"mode":"5m","signalsCount":0,"cycleProfileMs":{}},{"at":"2026-04-10T13:11:40.522Z","cycleMs":1,"ok":true,"mode":"5m","signalsCount":0,"cycleProfileMs":{}},{"at":"2026-04-10T13:11:41.543Z","cycleMs":1,"ok":true,"mode":"5m","signalsCount":0,"cycleProfileMs":{}},{"at":"2026-04-10T13:11:42.563Z","cycleMs":1,"ok":true,"mode":"5m","signalsCount":0,"cycleProfileMs":{}},{"at":"2026-04-10T13:11:44.623Z","cycleMs":1,"ok":true,"mode":"5m","signalsCount":0,"cycleProfileMs":{}},{"at":"2026-04-10T13:11:47.684Z","cycleMs":1,"ok":true,"mode":"5m","signalsCount":0,"cycleProfileMs":{}},{"at":"2026-04-10T13:11:48.704Z","cycleMs":1,"ok":true,"mode":"5m","signalsCount":0,"cycleProfileMs":{}},{"at":"2026-04-10T13:11:50.737Z","cycleMs":1,"ok":true,"mode":"5m","signalsCount":0,"cycleProfileMs":{}},{"at":"2026-04-10T13:11:51.755Z","cycleMs":1,"ok":true,"mode":"5m","signalsCount":0,"cycleProfileMs":{}},{"at":"2026-04-10T13:11:52.768Z","cycleMs":1,"ok":true,"mode":"5m","signalsCount":0,"cycleProfileMs":{}},{"at":"2026-04-10T13:11:53.792Z","cycleMs":1,"ok":true,"mode":"5m","signalsCount":0,"cycleProfileMs":{}},{"at":"2026-04-10T13:11:55.833Z","cycleMs":1,"ok":true,"mode":"5m","signalsCount":0,"cycleProfileMs":{}},{"at":"2026-04-10T13:11:57.885Z","cycleMs":1,"ok":true,"mode":"5m","signalsCount":0,"cycleProfileMs":{}},{"at":"2026-04-10T13:11:58.899Z","cycleMs":1,"ok":true,"mode":"5m","signalsCount":0,"cycleProfileMs":{}},{"at":"2026-04-10T13:12:00.929Z","cycleMs":1,"ok":true,"mode":"5m","signalsCount":0,"cycleProfileMs":{}},{"at":"2026-04-10T13:12:01.953Z","cycleMs":1,"ok":true,"mode":"5m","signalsCount":0,"cycleProfileMs":{}},{"at":"2026-04-10T13:12:02.967Z","cycleMs":1,"ok":true,"mode":"5m","signalsCount":0,"cycleProfileMs":{}},{"at":"2026-04-10T13:12:05.011Z","cycleMs":1,"ok":true,"mode":"5m","signalsCount":0,"cycleProfileMs":{}},{"at":"2026-04-10T13:12:06.038Z","cycleMs":1,"ok":true,"mode":"5m","signalsCount":0,"cycleProfileMs":{}},{"at":"2026-04-10T13:12:07.050Z","cycleMs":1,"ok":true,"mode":"5m","signalsCount":0,"cycleProfileMs":{}},{"at":"2026-04-10T13:12:09.073Z","cycleMs":1,"ok":true,"mode":"5m","signalsCount":0,"cycleProfileMs":{}},{"at":"2026-04-10T13:12:10.094Z","cycleMs":1,"ok":true,"mode":"5m","signalsCount":0,"cycleProfileMs":{}},{"at":"2026-04-10T13:12:11.114Z","cycleMs":1,"ok":true,"mode":"5m","signalsCount":0,"cycleProfileMs":{}},{"at":"2026-04-10T13:12:13.141Z","cycleMs":1,"ok":true,"mode":"5m","signalsCount":0,"cycleProfileMs":{}},{"at":"2026-04-10T13:12:18.214Z","cycleMs":1,"ok":true,"mode":"5m","signalsCount":0,"cycleProfileMs":{}},{"at":"2026-04-10T13:12:21.276Z","cycleMs":1,"ok":true,"mode":"5m","signalsCount":0,"cycleProfileMs":{}},{"at":"2026-04-10T13:12:22.288Z","cycleMs":1,"ok":true,"mode":"5m","signalsCount":0,"cycleProfileMs":{}},{"at":"2026-04-10T13:12:26.358Z","cycleMs":1,"ok":true,"mode":"5m","signalsCount":0,"cycleProfileMs":{}},{"at":"2026-04-10T13:12:28.392Z","cycleMs":1,"ok":true,"mode":"5m","signalsCount":0,"cycleProfileMs":{}},{"at":"2026-04-10T13:12:29.410Z","cycleMs":1,"ok":true,"mode":"5m","signalsCount":0,"cycleProfileMs":{}},{"at":"2026-04-10T13:12:30.435Z","cycleMs":1,"ok":true,"mode":"5m","signalsCount":0,"cycleProfileMs":{}},{"at":"2026-04-10T13:12:34.504Z","cycleMs":1,"ok":true,"mode":"5m","signalsCount":0,"cycleProfileMs":{}},{"at":"2026-04-10T13:12:35.517Z","cycleMs":1,"ok":true,"mode":"5m","signalsCount":0,"cycleProfileMs":{}},{"at":"2026-04-10T13:12:36.533Z","cycleMs":1,"ok":true,"mode":"5m","signalsCount":0,"cycleProfileMs":{}},{"at":"2026-04-10T13:12:38.560Z","cycleMs":1,"ok":true,"mode":"5m","signalsCount":0,"cycleProfileMs":{}},{"at":"2026-04-10T13:12:40.593Z","cycleMs":1,"ok":true,"mode":"5m","signalsCount":0,"cycleProfileMs":{}},{"at":"2026-04-10T13:12:41.610Z","cycleMs":1,"ok":true,"mode":"5m","signalsCount":0,"cycleProfileMs":{}},{"at":"2026-04-10T13:12:42.639Z","cycleMs":1,"ok":true,"mode":"5m","signalsCount":0,"cycleProfileMs":{}},{"at":"2026-04-10T13:12:44.681Z","cycleMs":1,"ok":true,"mode":"5m","signalsCount":0,"cycleProfileMs":{}},{"at":"2026-04-10T13:12:45.703Z","cycleMs":1,"ok":true,"mode":"5m","signalsCount":0,"cycleProfileMs":{}},{"at":"2026-04-10T13:12:46.723Z","cycleMs":1,"ok":true,"mode":"5m","signalsCount":0,"cycleProfileMs":{}},{"at":"2026-04-10T13:12:47.739Z","cycleMs":1,"ok":true,"mode":"5m","signalsCount":0,"cycleProfileMs":{}},{"at":"2026-04-10T13:12:49.770Z","cycleMs":1,"ok":true,"mode":"5m","signalsCount":0,"cycleProfileMs":{}},{"at":"2026-04-10T13:12:51.807Z","cycleMs":1,"ok":true,"mode":"5m","signalsCount":0,"cycleProfileMs":{}},{"at":"2026-04-10T13:12:53.833Z","cycleMs":1,"ok":true,"mode":"5m","signalsCount":0,"cycleProfileMs":{}},{"at":"2026-04-10T13:12:54.857Z","cycleMs":1,"ok":true,"mode":"5m","signalsCount":0,"cycleProfileMs":{}},{"at":"2026-04-10T13:12:56.893Z","cycleMs":1,"ok":true,"mode":"5m","signalsCount":0,"cycleProfileMs":{}},{"at":"2026-04-10T13:12:59.944Z","cycleMs":1,"ok":true,"mode":"5m","signalsCount":0,"cycleProfileMs":{}},{"at":"2026-04-10T13:13:01.992Z","cycleMs":1,"ok":true,"mode":"5m","signalsCount":0,"cycleProfileMs":{}},{"at":"2026-04-10T13:13:03.017Z","cycleMs":1,"ok":true,"mode":"5m","signalsCount":0,"cycleProfileMs":{}},{"at":"2026-04-10T13:13:05.057Z","cycleMs":1,"ok":true,"mode":"5m","signalsCount":0,"cycleProfileMs":{}},{"at":"2026-04-10T13:13:06.080Z","cycleMs":1,"ok":true,"mode":"5m","signalsCount":0,"cycleProfileMs":{}},{"at":"2026-04-10T13:13:08.121Z","cycleMs":1,"ok":true,"mode":"5m","signalsCount":0,"cycleProfileMs":{}},{"at":"2026-04-10T13:13:11.169Z","cycleMs":1,"ok":true,"mode":"5m","signalsCount":0,"cycleProfileMs":{}},{"at":"2026-04-10T13:13:14.234Z","cycleMs":5,"ok":true,"mode":"5m","signalsCount":0,"cycleProfileMs":{}},{"at":"2026-04-10T13:13:16.279Z","cycleMs":1,"ok":true,"mode":"5m","signalsCount":0,"cycleProfileMs":{}},{"at":"2026-04-10T13:13:18.309Z","cycleMs":1,"ok":true,"mode":"5m","signalsCount":0,"cycleProfileMs":{}},{"at":"2026-04-10T13:13:19.323Z","cycleMs":1,"ok":true,"mode":"5m","signalsCount":0,"cycleProfileMs":{}},{"at":"2026-04-10T13:13:21.346Z","cycleMs":1,"ok":true,"mode":"5m","signalsCount":0,"cycleProfileMs":{}},{"at":"2026-04-10T13:13:29.483Z","cycleMs":1,"ok":true,"mode":"5m","signalsCount":0,"cycleProfileMs":{}},{"at":"2026-04-10T13:13:34.547Z","cycleMs":1,"ok":true,"mode":"5m","signalsCount":0,"cycleProfileMs":{}},{"at":"2026-04-10T13:13:35.569Z","cycleMs":1,"ok":true,"mode":"5m","signalsCount":0,"cycleProfileMs":{}},{"at":"2026-04-10T13:13:36.588Z","cycleMs":1,"ok":true,"mode":"5m","signalsCount":0,"cycleProfileMs":{}},{"at":"2026-04-10T13:13:41.687Z","cycleMs":1,"ok":true,"mode":"5m","signalsCount":0,"cycleProfileMs":{}},{"at":"2026-04-10T13:13:42.714Z","cycleMs":1,"ok":true,"mode":"5m","signalsCount":0,"cycleProfileMs":{}},{"at":"2026-04-10T13:13:43.738Z","cycleMs":1,"ok":true,"mode":"5m","signalsCount":0,"cycleProfileMs":{}},{"at":"2026-04-10T13:13:44.761Z","cycleMs":1,"ok":true,"mode":"5m","signalsCount":0,"cycleProfileMs":{}},{"at":"2026-04-10T13:13:47.819Z","cycleMs":1,"ok":true,"mode":"5m","signalsCount":0,"cycleProfileMs":{}},{"at":"2026-04-10T13:13:49.859Z","cycleMs":1,"ok":true,"mode":"5m","signalsCount":0,"cycleProfileMs":{}},{"at":"2026-04-10T13:13:51.927Z","cycleMs":1,"ok":true,"mode":"5m","signalsCount":0,"cycleProfileMs":{}},{"at":"2026-04-10T13:13:55.999Z","cycleMs":1,"ok":true,"mode":"5m","signalsCount":0,"cycleProfileMs":{}},{"at":"2026-04-10T13:14:02.115Z","cycleMs":1,"ok":true,"mode":"5m","signalsCount":0,"cycleProfileMs":{}},{"at":"2026-04-10T13:14:03.144Z","cycleMs":1,"ok":true,"mode":"5m","signalsCount":0,"cycleProfileMs":{}},{"at":"2026-04-10T13:14:04.161Z","cycleMs":1,"ok":true,"mode":"5m","signalsCount":0,"cycleProfileMs":{}},{"at":"2026-04-10T13:14:06.209Z","cycleMs":1,"ok":true,"mode":"5m","signalsCount":0,"cycleProfileMs":{}},{"at":"2026-04-10T13:14:07.247Z","cycleMs":1,"ok":true,"mode":"5m","signalsCount":0,"cycleProfileMs":{}},{"at":"2026-04-10T13:14:09.322Z","cycleMs":1,"ok":true,"mode":"5m","signalsCount":0,"cycleProfileMs":{}},{"at":"2026-04-10T13:14:10.349Z","cycleMs":1,"ok":true,"mode":"5m","signalsCount":0,"cycleProfileMs":{}},{"at":"2026-04-10T13:14:12.397Z","cycleMs":1,"ok":true,"mode":"5m","signalsCount":0,"cycleProfileMs":{}},{"at":"2026-04-10T13:14:14.451Z","cycleMs":1,"ok":true,"mode":"5m","signalsCount":0,"cycleProfileMs":{}},{"at":"2026-04-10T13:14:15.472Z","cycleMs":1,"ok":true,"mode":"5m","signalsCount":0,"cycleProfileMs":{}},{"at":"2026-04-10T13:14:16.493Z","cycleMs":1,"ok":true,"mode":"5m","signalsCount":0,"cycleProfileMs":{}},{"at":"2026-04-10T13:14:17.520Z","cycleMs":1,"ok":true,"mode":"5m","signalsCount":0,"cycleProfileMs":{}},{"at":"2026-04-10T13:14:18.538Z","cycleMs":1,"ok":true,"mode":"5m","signalsCount":0,"cycleProfileMs":{}},{"at":"2026-04-10T13:14:23.634Z","cycleMs":1,"ok":true,"mode":"5m","signalsCount":0,"cycleProfileMs":{}},{"at":"2026-04-10T13:14:25.688Z","cycleMs":1,"ok":true,"mode":"5m","signalsCount":0,"cycleProfileMs":{}},{"at":"2026-04-10T13:14:29.769Z","cycleMs":1,"ok":true,"mode":"5m","signalsCount":0,"cycleProfileMs":{}},{"at":"2026-04-10T13:14:34.837Z","cycleMs":1,"ok":true,"mode":"5m","signalsCount":0,"cycleProfileMs":{}},{"at":"2026-04-10T13:14:45.054Z","cycleMs":1,"ok":true,"mode":"5m","signalsCount":0,"cycleProfileMs":{}},{"at":"2026-04-10T13:14:48.087Z","cycleMs":1,"ok":true,"mode":"5m","signalsCount":0,"cycleProfileMs":{}},{"at":"2026-04-10T13:14:49.108Z","cycleMs":1,"ok":true,"mode":"5m","signalsCount":0,"cycleProfileMs":{}},{"at":"2026-04-10T13:14:53.183Z","cycleMs":1,"ok":true,"mode":"5m","signalsCount":0,"cycleProfileMs":{}},{"at":"2026-04-10T13:14:55.234Z","cycleMs":1,"ok":true,"mode":"5m","signalsCount":0,"cycleProfileMs":{}},{"at":"2026-04-10T13:14:56.258Z","cycleMs":1,"ok":true,"mode":"5m","signalsCount":0,"cycleProfileMs":{}},{"at":"2026-04-10T13:14:58.290Z","cycleMs":1,"ok":true,"mode":"5m","signalsCount":0,"cycleProfileMs":{}},{"at":"2026-04-10T13:15:00.328Z","cycleMs":1,"ok":true,"mode":"5m","signalsCount":0,"cycleProfileMs":{}},{"at":"2026-04-10T13:15:02.363Z","cycleMs":1,"ok":true,"mode":"5m","signalsCount":0,"cycleProfileMs":{}},{"at":"2026-04-10T13:15:05.425Z","cycleMs":1,"ok":true,"mode":"5m","signalsCount":0,"cycleProfileMs":{}},{"at":"2026-04-10T13:15:08.499Z","cycleMs":1,"ok":true,"mode":"5m","signalsCount":0,"cycleProfileMs":{}},{"at":"2026-04-10T13:15:09.523Z","cycleMs":1,"ok":true,"mode":"5m","signalsCount":0,"cycleProfileMs":{}},{"at":"2026-04-10T13:15:10.553Z","cycleMs":1,"ok":true,"mode":"5m","signalsCount":0,"cycleProfileMs":{}},{"at":"2026-04-10T13:15:12.590Z","cycleMs":1,"ok":true,"mode":"5m","signalsCount":0,"cycleProfileMs":{}},{"at":"2026-04-10T13:15:13.613Z","cycleMs":1,"ok":true,"mode":"5m","signalsCount":0,"cycleProfileMs":{}},{"at":"2026-04-10T13:15:15.658Z","cycleMs":1,"ok":true,"mode":"5m","signalsCount":0,"cycleProfileMs":{}},{"at":"2026-04-10T13:15:17.691Z","cycleMs":1,"ok":true,"mode":"5m","signalsCount":0,"cycleProfileMs":{}},{"at":"2026-04-10T13:15:19.720Z","cycleMs":1,"ok":true,"mode":"5m","signalsCount":0,"cycleProfileMs":{}},{"at":"2026-04-10T13:15:20.742Z","cycleMs":1,"ok":true,"mode":"5m","signalsCount":0,"cycleProfileMs":{}},{"at":"2026-04-10T13:15:21.783Z","cycleMs":1,"ok":true,"mode":"5m","signalsCount":0,"cycleProfileMs":{}},{"at":"2026-04-10T13:15:23.817Z","cycleMs":1,"ok":true,"mode":"5m","signalsCount":0,"cycleProfileMs":{}},{"at":"2026-04-10T13:15:26.870Z","cycleMs":1,"ok":true,"mode":"5m","signalsCount":0,"cycleProfileMs":{}},{"at":"2026-04-10T13:15:27.894Z","cycleMs":1,"ok":true,"mode":"5m","signalsCount":0,"cycleProfileMs":{}},{"at":"2026-04-10T13:15:28.912Z","cycleMs":1,"ok":true,"mode":"5m","signalsCount":0,"cycleProfileMs":{}},{"at":"2026-04-10T13:15:30.958Z","cycleMs":1,"ok":true,"mode":"5m","signalsCount":0,"cycleProfileMs":{}},{"at":"2026-04-10T13:15:31.972Z","cycleMs":1,"ok":true,"mode":"5m","signalsCount":0,"cycleProfileMs":{}},{"at":"2026-04-10T13:15:35.029Z","cycleMs":1,"ok":true,"mode":"5m","signalsCount":0,"cycleProfileMs":{}},{"at":"2026-04-10T13:15:36.042Z","cycleMs":1,"ok":true,"mode":"5m","signalsCount":0,"cycleProfileMs":{}},{"at":"2026-04-10T13:15:40.117Z","cycleMs":1,"ok":true,"mode":"5m","signalsCount":0,"cycleProfileMs":{}},{"at":"2026-04-10T13:15:41.138Z","cycleMs":1,"ok":true,"mode":"5m","signalsCount":0,"cycleProfileMs":{}},{"at":"2026-04-10T13:15:43.178Z","cycleMs":1,"ok":true,"mode":"5m","signalsCount":0,"cycleProfileMs":{}},{"at":"2026-04-10T13:15:46.242Z","cycleMs":1,"ok":true,"mode":"5m","signalsCount":0,"cycleProfileMs":{}},{"at":"2026-04-10T13:15:48.278Z","cycleMs":1,"ok":true,"mode":"5m","signalsCount":0,"cycleProfileMs":{}},{"at":"2026-04-10T13:15:50.326Z","cycleMs":1,"ok":true,"mode":"5m","signalsCount":0,"cycleProfileMs":{}},{"at":"2026-04-10T13:15:53.374Z","cycleMs":1,"ok":true,"mode":"5m","signalsCount":0,"cycleProfileMs":{}},{"at":"2026-04-10T13:15:55.402Z","cycleMs":1,"ok":true,"mode":"5m","signalsCount":0,"cycleProfileMs":{}},{"at":"2026-04-10T13:15:56.422Z","cycleMs":1,"ok":true,"mode":"5m","signalsCount":0,"cycleProfileMs":{}},{"at":"2026-04-10T13:15:57.451Z","cycleMs":1,"ok":true,"mode":"5m","signalsCount":0,"cycleProfileMs":{}},{"at":"2026-04-10T13:15:58.472Z","cycleMs":1,"ok":true,"mode":"5m","signalsCount":0,"cycleProfileMs":{}},{"at":"2026-04-10T13:16:00.515Z","cycleMs":1,"ok":true,"mode":"5m","signalsCount":0,"cycleProfileMs":{}},{"at":"2026-04-10T13:16:07.655Z","cycleMs":1,"ok":true,"mode":"5m","signalsCount":0,"cycleProfileMs":{}},{"at":"2026-04-10T13:16:09.698Z","cycleMs":1,"ok":true,"mode":"5m","signalsCount":0,"cycleProfileMs":{}},{"at":"2026-04-10T13:16:17.848Z","cycleMs":1,"ok":true,"mode":"5m","signalsCount":0,"cycleProfileMs":{}},{"at":"2026-04-10T13:16:20.901Z","cycleMs":1,"ok":true,"mode":"5m","signalsCount":0,"cycleProfileMs":{}},{"at":"2026-04-10T13:16:21.920Z","cycleMs":1,"ok":true,"mode":"5m","signalsCount":0,"cycleProfileMs":{}},{"at":"2026-04-10T13:16:25.970Z","cycleMs":1,"ok":true,"mode":"5m","signalsCount":0,"cycleProfileMs":{}},{"at":"2026-04-10T13:16:30.041Z","cycleMs":1,"ok":true,"mode":"5m","signalsCount":0,"cycleProfileMs":{}},{"at":"2026-04-10T13:16:33.095Z","cycleMs":1,"ok":true,"mode":"5m","signalsCount":0,"cycleProfileMs":{}},{"at":"2026-04-10T13:16:34.116Z","cycleMs":1,"ok":true,"mode":"5m","signalsCount":0,"cycleProfileMs":{}},{"at":"2026-04-10T13:16:35.133Z","cycleMs":1,"ok":true,"mode":"5m","signalsCount":0,"cycleProfileMs":{}},{"at":"2026-04-10T13:16:37.171Z","cycleMs":1,"ok":true,"mode":"5m","signalsCount":0,"cycleProfileMs":{}},{"at":"2026-04-10T13:16:38.189Z","cycleMs":1,"ok":true,"mode":"5m","signalsCount":0,"cycleProfileMs":{}},{"at":"2026-04-10T13:16:39.196Z","cycleMs":1,"ok":true,"mode":"5m","signalsCount":0,"cycleProfileMs":{}},{"at":"2026-04-10T13:16:44.298Z","cycleMs":1,"ok":true,"mode":"5m","signalsCount":0,"cycleProfileMs":{}},{"at":"2026-04-10T13:16:47.341Z","cycleMs":1,"ok":true,"mode":"5m","signalsCount":0,"cycleProfileMs":{}},{"at":"2026-04-10T13:16:51.416Z","cycleMs":1,"ok":true,"mode":"5m","signalsCount":0,"cycleProfileMs":{}},{"at":"2026-04-10T13:16:54.472Z","cycleMs":1,"ok":true,"mode":"5m","signalsCount":0,"cycleProfileMs":{}},{"at":"2026-04-10T13:16:57.537Z","cycleMs":1,"ok":true,"mode":"5m","signalsCount":0,"cycleProfileMs":{}},{"at":"2026-04-10T13:17:00.590Z","cycleMs":1,"ok":true,"mode":"5m","signalsCount":0,"cycleProfileMs":{}},{"at":"2026-04-10T13:17:01.621Z","cycleMs":1,"ok":true,"mode":"5m","signalsCount":0,"cycleProfileMs":{}},{"at":"2026-04-10T13:17:04.684Z","cycleMs":1,"ok":true,"mode":"5m","signalsCount":0,"cycleProfileMs":{}},{"at":"2026-04-10T13:17:07.750Z","cycleMs":1,"ok":true,"mode":"5m","signalsCount":0,"cycleProfileMs":{}},{"at":"2026-04-10T13:17:10.839Z","cycleMs":1,"ok":true,"mode":"5m","signalsCount":0,"cycleProfileMs":{}},{"at":"2026-04-10T13:17:13.897Z","cycleMs":1,"ok":true,"mode":"5m","signalsCount":0,"cycleProfileMs":{}},{"at":"2026-04-10T13:17:14.916Z","cycleMs":1,"ok":true,"mode":"5m","signalsCount":0,"cycleProfileMs":{}},{"at":"2026-04-10T13:17:16.974Z","cycleMs":1,"ok":true,"mode":"5m","signalsCount":0,"cycleProfileMs":{}},{"at":"2026-04-10T13:17:19.017Z","cycleMs":1,"ok":true,"mode":"5m","signalsCount":0,"cycleProfileMs":{}},{"at":"2026-04-10T13:17:20.036Z","cycleMs":1,"ok":true,"mode":"5m","signalsCount":0,"cycleProfileMs":{}},{"at":"2026-04-10T13:17:27.167Z","cycleMs":1,"ok":true,"mode":"5m","signalsCount":0,"cycleProfileMs":{}},{"at":"2026-04-10T13:17:30.222Z","cycleMs":1,"ok":true,"mode":"5m","signalsCount":0,"cycleProfileMs":{}},{"at":"2026-04-10T13:17:34.307Z","cycleMs":1,"ok":true,"mode":"5m","signalsCount":0,"cycleProfileMs":{}},{"at":"2026-04-10T13:17:36.348Z","cycleMs":1,"ok":true,"mode":"5m","signalsCount":0,"cycleProfileMs":{}},{"at":"2026-04-10T13:17:39.402Z","cycleMs":1,"ok":true,"mode":"5m","signalsCount":0,"cycleProfileMs":{}},{"at":"2026-04-10T13:17:41.437Z","cycleMs":1,"ok":true,"mode":"5m","signalsCount":0,"cycleProfileMs":{}},{"at":"2026-04-10T13:17:42.456Z","cycleMs":1,"ok":true,"mode":"5m","signalsCount":0,"cycleProfileMs":{}},{"at":"2026-04-10T13:17:44.481Z","cycleMs":1,"ok":true,"mode":"5m","signalsCount":0,"cycleProfileMs":{}},{"at":"2026-04-10T13:17:47.523Z","cycleMs":1,"ok":true,"mode":"5m","signalsCount":0,"cycleProfileMs":{}},{"at":"2026-04-10T13:17:56.681Z","cycleMs":1,"ok":true,"mode":"5m","signalsCount":0,"cycleProfileMs":{}},{"at":"2026-04-10T13:18:03.806Z","cycleMs":1,"ok":true,"mode":"5m","signalsCount":0,"cycleProfileMs":{}},{"at":"2026-04-10T13:18:06.863Z","cycleMs":1,"ok":true,"mode":"5m","signalsCount":0,"cycleProfileMs":{}},{"at":"2026-04-10T13:18:09.906Z","cycleMs":1,"ok":true,"mode":"5m","signalsCount":0,"cycleProfileMs":{}},{"at":"2026-04-10T13:18:10.923Z","cycleMs":1,"ok":true,"mode":"5m","signalsCount":0,"cycleProfileMs":{}},{"at":"2026-04-10T13:18:11.943Z","cycleMs":1,"ok":true,"mode":"5m","signalsCount":0,"cycleProfileMs":{}},{"at":"2026-04-10T13:18:13.978Z","cycleMs":1,"ok":true,"mode":"5m","signalsCount":0,"cycleProfileMs":{}},{"at":"2026-04-10T13:18:17.036Z","cycleMs":1,"ok":true,"mode":"5m","signalsCount":0,"cycleProfileMs":{}},{"at":"2026-04-10T13:18:18.056Z","cycleMs":1,"ok":true,"mode":"5m","signalsCount":0,"cycleProfileMs":{}},{"at":"2026-04-10T13:18:21.102Z","cycleMs":1,"ok":true,"mode":"5m","signalsCount":0,"cycleProfileMs":{}},{"at":"2026-04-10T13:18:23.151Z","cycleMs":1,"ok":true,"mode":"5m","signalsCount":0,"cycleProfileMs":{}},{"at":"2026-04-10T13:18:30.273Z","cycleMs":1,"ok":true,"mode":"5m","signalsCount":0,"cycleProfileMs":{}},{"at":"2026-04-10T13:18:32.315Z","cycleMs":1,"ok":true,"mode":"5m","signalsCount":0,"cycleProfileMs":{}},{"at":"2026-04-10T13:18:33.339Z","cycleMs":1,"ok":true,"mode":"5m","signalsCount":0,"cycleProfileMs":{}},{"at":"2026-04-10T13:18:34.353Z","cycleMs":1,"ok":true,"mode":"5m","signalsCount":0,"cycleProfileMs":{}},{"at":"2026-04-10T13:18:38.417Z","cycleMs":1,"ok":true,"mode":"5m","signalsCount":0,"cycleProfileMs":{}},{"at":"2026-04-10T13:18:39.440Z","cycleMs":1,"ok":true,"mode":"5m","signalsCount":0,"cycleProfileMs":{}},{"at":"2026-04-10T13:18:41.474Z","cycleMs":1,"ok":true,"mode":"5m","signalsCount":0,"cycleProfileMs":{}},{"at":"2026-04-10T13:18:44.538Z","cycleMs":1,"ok":true,"mode":"5m","signalsCount":0,"cycleProfileMs":{}},{"at":"2026-04-10T13:18:45.563Z","cycleMs":1,"ok":true,"mode":"5m","signalsCount":0,"cycleProfileMs":{}},{"at":"2026-04-10T13:18:47.604Z","cycleMs":1,"ok":true,"mode":"5m","signalsCount":0,"cycleProfileMs":{}},{"at":"2026-04-10T13:18:48.625Z","cycleMs":1,"ok":true,"mode":"5m","signalsCount":0,"cycleProfileMs":{}},{"at":"2026-04-10T13:18:51.695Z","cycleMs":1,"ok":true,"mode":"5m","signalsCount":0,"cycleProfileMs":{}},{"at":"2026-04-10T13:18:53.720Z","cycleMs":1,"ok":true,"mode":"5m","signalsCount":0,"cycleProfileMs":{}},{"at":"2026-04-10T13:18:55.762Z","cycleMs":1,"ok":true,"mode":"5m","signalsCount":0,"cycleProfileMs":{}},{"at":"2026-04-10T13:18:56.788Z","cycleMs":1,"ok":true,"mode":"5m","signalsCount":0,"cycleProfileMs":{}},{"at":"2026-04-10T13:18:58.819Z","cycleMs":1,"ok":true,"mode":"5m","signalsCount":0,"cycleProfileMs":{}},{"at":"2026-04-10T13:19:04.934Z","cycleMs":1,"ok":true,"mode":"5m","signalsCount":0,"cycleProfileMs":{}},{"at":"2026-04-10T13:19:05.958Z","cycleMs":1,"ok":true,"mode":"5m","signalsCount":0,"cycleProfileMs":{}},{"at":"2026-04-10T13:19:09.025Z","cycleMs":1,"ok":true,"mode":"5m","signalsCount":0,"cycleProfileMs":{}},{"at":"2026-04-10T13:19:10.053Z","cycleMs":1,"ok":true,"mode":"5m","signalsCount":0,"cycleProfileMs":{}},{"at":"2026-04-10T13:19:11.081Z","cycleMs":1,"ok":true,"mode":"5m","signalsCount":0,"cycleProfileMs":{}},{"at":"2026-04-10T13:19:13.107Z","cycleMs":1,"ok":true,"mode":"5m","signalsCount":0,"cycleProfileMs":{}},{"at":"2026-04-10T13:19:15.140Z","cycleMs":1,"ok":true,"mode":"5m","signalsCount":0,"cycleProfileMs":{}},{"at":"2026-04-10T13:19:19.210Z","cycleMs":1,"ok":true,"mode":"5m","signalsCount":0,"cycleProfileMs":{}},{"at":"2026-04-10T13:19:21.250Z","cycleMs":1,"ok":true,"mode":"5m","signalsCount":0,"cycleProfileMs":{}},{"at":"2026-04-10T13:19:23.297Z","cycleMs":1,"ok":true,"mode":"5m","signalsCount":0,"cycleProfileMs":{}},{"at":"2026-04-10T13:19:30.421Z","cycleMs":1,"ok":true,"mode":"5m","signalsCount":0,"cycleProfileMs":{}},{"at":"2026-04-10T13:19:32.455Z","cycleMs":1,"ok":true,"mode":"5m","signalsCount":0,"cycleProfileMs":{}},{"at":"2026-04-10T13:19:34.488Z","cycleMs":1,"ok":true,"mode":"5m","signalsCount":0,"cycleProfileMs":{}},{"at":"2026-04-10T13:19:36.523Z","cycleMs":1,"ok":true,"mode":"5m","signalsCount":0,"cycleProfileMs":{}},{"at":"2026-04-10T13:19:37.541Z","cycleMs":1,"ok":true,"mode":"5m","signalsCount":0,"cycleProfileMs":{}},{"at":"2026-04-10T13:19:42.637Z","cycleMs":1,"ok":true,"mode":"5m","signalsCount":0,"cycleProfileMs":{}},{"at":"2026-04-10T13:19:43.661Z","cycleMs":1,"ok":true,"mode":"5m","signalsCount":0,"cycleProfileMs":{}},{"at":"2026-04-10T13:19:46.698Z","cycleMs":1,"ok":true,"mode":"5m","signalsCount":0,"cycleProfileMs":{}},{"at":"2026-04-10T13:19:47.720Z","cycleMs":1,"ok":true,"mode":"5m","signalsCount":0,"cycleProfileMs":{}},{"at":"2026-04-10T13:19:50.765Z","cycleMs":1,"ok":true,"mode":"5m","signalsCount":0,"cycleProfileMs":{}},{"at":"2026-04-10T13:19:51.793Z","cycleMs":1,"ok":true,"mode":"5m","signalsCount":0,"cycleProfileMs":{}},{"at":"2026-04-10T13:19:56.884Z","cycleMs":1,"ok":true,"mode":"5m","signalsCount":0,"cycleProfileMs":{}},{"at":"2026-04-10T13:19:57.902Z","cycleMs":1,"ok":true,"mode":"5m","signalsCount":0,"cycleProfileMs":{}},{"at":"2026-04-10T13:20:11.142Z","cycleMs":1,"ok":true,"mode":"5m","signalsCount":0,"cycleProfileMs":{}},{"at":"2026-04-10T13:20:12.167Z","cycleMs":1,"ok":true,"mode":"5m","signalsCount":0,"cycleProfileMs":{}},{"at":"2026-04-10T13:20:15.209Z","cycleMs":1,"ok":true,"mode":"5m","signalsCount":0,"cycleProfileMs":{}},{"at":"2026-04-10T13:20:17.255Z","cycleMs":1,"ok":true,"mode":"5m","signalsCount":0,"cycleProfileMs":{}},{"at":"2026-04-10T13:20:18.279Z","cycleMs":1,"ok":true,"mode":"5m","signalsCount":0,"cycleProfileMs":{}},{"at":"2026-04-10T13:20:20.308Z","cycleMs":1,"ok":true,"mode":"5m","signalsCount":0,"cycleProfileMs":{}},{"at":"2026-04-10T13:20:21.321Z","cycleMs":1,"ok":true,"mode":"5m","signalsCount":0,"cycleProfileMs":{}},{"at":"2026-04-10T13:20:22.340Z","cycleMs":1,"ok":true,"mode":"5m","signalsCount":0,"cycleProfileMs":{}},{"at":"2026-04-10T13:20:23.358Z","cycleMs":1,"ok":true,"mode":"5m","signalsCount":0,"cycleProfileMs":{}},{"at":"2026-04-10T13:20:24.377Z","cycleMs":1,"ok":true,"mode":"5m","signalsCount":0,"cycleProfileMs":{}},{"at":"2026-04-10T13:20:25.399Z","cycleMs":1,"ok":true,"mode":"5m","signalsCount":0,"cycleProfileMs":{}},{"at":"2026-04-10T13:20:28.459Z","cycleMs":1,"ok":true,"mode":"5m","signalsCount":0,"cycleProfileMs":{}},{"at":"2026-04-10T13:20:30.508Z","cycleMs":1,"ok":true,"mode":"5m","signalsCount":0,"cycleProfileMs":{}},{"at":"2026-04-10T13:20:31.519Z","cycleMs":1,"ok":true,"mode":"5m","signalsCount":0,"cycleProfileMs":{}},{"at":"2026-04-10T13:20:32.539Z","cycleMs":1,"ok":true,"mode":"5m","signalsCount":0,"cycleProfileMs":{}},{"at":"2026-04-10T13:20:34.564Z","cycleMs":1,"ok":true,"mode":"5m","signalsCount":0,"cycleProfileMs":{}},{"at":"2026-04-10T13:20:38.653Z","cycleMs":1,"ok":true,"mode":"5m","signalsCount":0,"cycleProfileMs":{}},{"at":"2026-04-10T13:20:40.693Z","cycleMs":1,"ok":true,"mode":"5m","signalsCount":0,"cycleProfileMs":{}},{"at":"2026-04-10T13:20:42.728Z","cycleMs":1,"ok":true,"mode":"5m","signalsCount":0,"cycleProfileMs":{}},{"at":"2026-04-10T13:20:43.751Z","cycleMs":1,"ok":true,"mode":"5m","signalsCount":0,"cycleProfileMs":{}},{"at":"2026-04-10T13:20:45.788Z","cycleMs":1,"ok":true,"mode":"5m","signalsCount":0,"cycleProfileMs":{}},{"at":"2026-04-10T13:20:50.859Z","cycleMs":1,"ok":true,"mode":"5m","signalsCount":0,"cycleProfileMs":{}},{"at":"2026-04-10T13:20:54.907Z","cycleMs":1,"ok":true,"mode":"5m","signalsCount":0,"cycleProfileMs":{}},{"at":"2026-04-10T13:20:56.954Z","cycleMs":1,"ok":true,"mode":"5m","signalsCount":0,"cycleProfileMs":{}},{"at":"2026-04-10T13:20:57.973Z","cycleMs":1,"ok":true,"mode":"5m","signalsCount":0,"cycleProfileMs":{}},{"at":"2026-04-10T13:20:59.991Z","cycleMs":1,"ok":true,"mode":"5m","signalsCount":0,"cycleProfileMs":{}},{"at":"2026-04-10T13:21:02.017Z","cycleMs":1,"ok":true,"mode":"5m","signalsCount":0,"cycleProfileMs":{}},{"at":"2026-04-10T13:21:04.052Z","cycleMs":1,"ok":true,"mode":"5m","signalsCount":0,"cycleProfileMs":{}},{"at":"2026-04-10T13:21:05.066Z","cycleMs":1,"ok":true,"mode":"5m","signalsCount":0,"cycleProfileMs":{}},{"at":"2026-04-10T13:21:06.090Z","cycleMs":1,"ok":true,"mode":"5m","signalsCount":0,"cycleProfileMs":{}},{"at":"2026-04-10T13:21:13.196Z","cycleMs":2,"ok":true,"mode":"5m","signalsCount":0,"cycleProfileMs":{}},{"at":"2026-04-10T13:21:16.254Z","cycleMs":1,"ok":true,"mode":"5m","signalsCount":0,"cycleProfileMs":{}},{"at":"2026-04-10T13:21:20.317Z","cycleMs":1,"ok":true,"mode":"5m","signalsCount":0,"cycleProfileMs":{}},{"at":"2026-04-10T13:21:23.383Z","cycleMs":1,"ok":true,"mode":"5m","signalsCount":0,"cycleProfileMs":{}},{"at":"2026-04-10T13:21:33.556Z","cycleMs":1,"ok":true,"mode":"5m","signalsCount":0,"cycleProfileMs":{}},{"at":"2026-04-10T13:21:36.605Z","cycleMs":1,"ok":true,"mode":"5m","signalsCount":0,"cycleProfileMs":{}},{"at":"2026-04-10T13:21:38.627Z","cycleMs":1,"ok":true,"mode":"5m","signalsCount":0,"cycleProfileMs":{}},{"at":"2026-04-10T13:21:39.642Z","cycleMs":1,"ok":true,"mode":"5m","signalsCount":0,"cycleProfileMs":{}},{"at":"2026-04-10T13:21:43.708Z","cycleMs":1,"ok":true,"mode":"5m","signalsCount":0,"cycleProfileMs":{}},{"at":"2026-04-10T13:21:48.819Z","cycleMs":1,"ok":true,"mode":"5m","signalsCount":0,"cycleProfileMs":{}},{"at":"2026-04-10T13:21:49.833Z","cycleMs":1,"ok":true,"mode":"5m","signalsCount":0,"cycleProfileMs":{}},{"at":"2026-04-10T13:21:51.884Z","cycleMs":1,"ok":true,"mode":"5m","signalsCount":0,"cycleProfileMs":{}},{"at":"2026-04-10T13:21:53.907Z","cycleMs":1,"ok":true,"mode":"5m","signalsCount":0,"cycleProfileMs":{}},{"at":"2026-04-10T13:21:54.926Z","cycleMs":2,"ok":true,"mode":"5m","signalsCount":0,"cycleProfileMs":{}},{"at":"2026-04-10T13:21:56.963Z","cycleMs":1,"ok":true,"mode":"5m","signalsCount":0,"cycleProfileMs":{}},{"at":"2026-04-10T13:21:57.976Z","cycleMs":1,"ok":true,"mode":"5m","signalsCount":0,"cycleProfileMs":{}},{"at":"2026-04-10T13:21:59.000Z","cycleMs":1,"ok":true,"mode":"5m","signalsCount":0,"cycleProfileMs":{}},{"at":"2026-04-10T13:22:04.101Z","cycleMs":1,"ok":true,"mode":"5m","signalsCount":0,"cycleProfileMs":{}},{"at":"2026-04-10T13:22:05.126Z","cycleMs":1,"ok":true,"mode":"5m","signalsCount":0,"cycleProfileMs":{}},{"at":"2026-04-10T13:22:07.166Z","cycleMs":1,"ok":true,"mode":"5m","signalsCount":0,"cycleProfileMs":{}},{"at":"2026-04-10T13:22:08.179Z","cycleMs":1,"ok":true,"mode":"5m","signalsCount":0,"cycleProfileMs":{}},{"at":"2026-04-10T13:22:09.197Z","cycleMs":1,"ok":true,"mode":"5m","signalsCount":0,"cycleProfileMs":{}},{"at":"2026-04-10T13:22:12.233Z","cycleMs":1,"ok":true,"mode":"5m","signalsCount":0,"cycleProfileMs":{}},{"at":"2026-04-10T13:22:13.261Z","cycleMs":1,"ok":true,"mode":"5m","signalsCount":0,"cycleProfileMs":{}},{"at":"2026-04-10T13:22:16.304Z","cycleMs":1,"ok":true,"mode":"5m","signalsCount":0,"cycleProfileMs":{}},{"at":"2026-04-10T13:22:20.352Z","cycleMs":1,"ok":true,"mode":"5m","signalsCount":0,"cycleProfileMs":{}},{"at":"2026-04-10T13:22:21.377Z","cycleMs":1,"ok":true,"mode":"5m","signalsCount":0,"cycleProfileMs":{}},{"at":"2026-04-10T13:22:23.396Z","cycleMs":1,"ok":true,"mode":"5m","signalsCount":0,"cycleProfileMs":{}},{"at":"2026-04-10T13:22:26.440Z","cycleMs":1,"ok":true,"mode":"5m","signalsCount":0,"cycleProfileMs":{}},{"at":"2026-04-10T13:22:28.482Z","cycleMs":1,"ok":true,"mode":"5m","signalsCount":0,"cycleProfileMs":{}},{"at":"2026-04-10T13:22:35.600Z","cycleMs":3,"ok":true,"mode":"5m","signalsCount":0,"cycleProfileMs":{}},{"at":"2026-04-10T13:22:36.625Z","cycleMs":1,"ok":true,"mode":"5m","signalsCount":0,"cycleProfileMs":{}},{"at":"2026-04-10T13:22:37.638Z","cycleMs":1,"ok":true,"mode":"5m","signalsCount":0,"cycleProfileMs":{}},{"at":"2026-04-10T13:22:38.664Z","cycleMs":1,"ok":true,"mode":"5m","signalsCount":0,"cycleProfileMs":{}},{"at":"2026-04-10T13:22:39.684Z","cycleMs":1,"ok":true,"mode":"5m","signalsCount":0,"cycleProfileMs":{}},{"at":"2026-04-10T13:22:41.711Z","cycleMs":1,"ok":true,"mode":"5m","signalsCount":0,"cycleProfileMs":{}},{"at":"2026-04-10T13:22:42.735Z","cycleMs":1,"ok":true,"mode":"5m","signalsCount":0,"cycleProfileMs":{}},{"at":"2026-04-10T13:22:43.759Z","cycleMs":1,"ok":true,"mode":"5m","signalsCount":0,"cycleProfileMs":{}},{"at":"2026-04-10T13:22:52.903Z","cycleMs":1,"ok":true,"mode":"5m","signalsCount":0,"cycleProfileMs":{}},{"at":"2026-04-10T13:22:53.925Z","cycleMs":1,"ok":true,"mode":"5m","signalsCount":0,"cycleProfileMs":{}},{"at":"2026-04-10T13:22:57.991Z","cycleMs":1,"ok":true,"mode":"5m","signalsCount":0,"cycleProfileMs":{}},{"at":"2026-04-10T13:23:00.034Z","cycleMs":1,"ok":true,"mode":"5m","signalsCount":0,"cycleProfileMs":{}},{"at":"2026-04-10T13:23:01.046Z","cycleMs":1,"ok":true,"mode":"5m","signalsCount":0,"cycleProfileMs":{}},{"at":"2026-04-10T13:23:03.093Z","cycleMs":1,"ok":true,"mode":"5m","signalsCount":0,"cycleProfileMs":{}},{"at":"2026-04-10T13:23:04.107Z","cycleMs":1,"ok":true,"mode":"5m","signalsCount":0,"cycleProfileMs":{}},{"at":"2026-04-10T13:23:10.189Z","cycleMs":1,"ok":true,"mode":"5m","signalsCount":0,"cycleProfileMs":{}},{"at":"2026-04-10T13:23:11.202Z","cycleMs":1,"ok":true,"mode":"5m","signalsCount":0,"cycleProfileMs":{}},{"at":"2026-04-10T13:23:13.238Z","cycleMs":1,"ok":true,"mode":"5m","signalsCount":0,"cycleProfileMs":{}},{"at":"2026-04-10T13:23:16.301Z","cycleMs":1,"ok":true,"mode":"5m","signalsCount":0,"cycleProfileMs":{}},{"at":"2026-04-10T13:23:17.316Z","cycleMs":1,"ok":true,"mode":"5m","signalsCount":0,"cycleProfileMs":{}},{"at":"2026-04-10T13:23:18.329Z","cycleMs":1,"ok":true,"mode":"5m","signalsCount":0,"cycleProfileMs":{}},{"at":"2026-04-10T13:23:21.367Z","cycleMs":1,"ok":true,"mode":"5m","signalsCount":0,"cycleProfileMs":{}},{"at":"2026-04-10T13:23:24.419Z","cycleMs":1,"ok":true,"mode":"5m","signalsCount":0,"cycleProfileMs":{}},{"at":"2026-04-10T13:23:31.511Z","cycleMs":1,"ok":true,"mode":"5m","signalsCount":0,"cycleProfileMs":{}},{"at":"2026-04-10T13:23:36.593Z","cycleMs":1,"ok":true,"mode":"5m","signalsCount":0,"cycleProfileMs":{}},{"at":"2026-04-10T13:23:41.657Z","cycleMs":1,"ok":true,"mode":"5m","signalsCount":0,"cycleProfileMs":{}},{"at":"2026-04-10T13:23:42.681Z","cycleMs":1,"ok":true,"mode":"5m","signalsCount":0,"cycleProfileMs":{}},{"at":"2026-04-10T13:23:43.705Z","cycleMs":1,"ok":true,"mode":"5m","signalsCount":0,"cycleProfileMs":{}},{"at":"2026-04-10T13:23:45.753Z","cycleMs":1,"ok":true,"mode":"5m","signalsCount":0,"cycleProfileMs":{}},{"at":"2026-04-10T13:23:47.777Z","cycleMs":1,"ok":true,"mode":"5m","signalsCount":0,"cycleProfileMs":{}},{"at":"2026-04-10T13:23:50.837Z","cycleMs":1,"ok":true,"mode":"5m","signalsCount":0,"cycleProfileMs":{}},{"at":"2026-04-10T13:23:55.935Z","cycleMs":1,"ok":true,"mode":"5m","signalsCount":0,"cycleProfileMs":{}},{"at":"2026-04-10T13:23:56.954Z","cycleMs":1,"ok":true,"mode":"5m","signalsCount":0,"cycleProfileMs":{}},{"at":"2026-04-10T13:23:58.977Z","cycleMs":1,"ok":true,"mode":"5m","signalsCount":0,"cycleProfileMs":{}},{"at":"2026-04-10T13:24:01.013Z","cycleMs":1,"ok":true,"mode":"5m","signalsCount":0,"cycleProfileMs":{}},{"at":"2026-04-10T13:24:03.044Z","cycleMs":1,"ok":true,"mode":"5m","signalsCount":0,"cycleProfileMs":{}},{"at":"2026-04-10T13:24:04.056Z","cycleMs":1,"ok":true,"mode":"5m","signalsCount":0,"cycleProfileMs":{}},{"at":"2026-04-10T13:24:05.081Z","cycleMs":1,"ok":true,"mode":"5m","signalsCount":0,"cycleProfileMs":{}},{"at":"2026-04-10T13:24:06.108Z","cycleMs":1,"ok":true,"mode":"5m","signalsCount":0,"cycleProfileMs":{}},{"at":"2026-04-10T13:24:09.159Z","cycleMs":1,"ok":true,"mode":"5m","signalsCount":0,"cycleProfileMs":{}},{"at":"2026-04-10T13:24:10.180Z","cycleMs":1,"ok":true,"mode":"5m","signalsCount":0,"cycleProfileMs":{}},{"at":"2026-04-10T13:24:11.199Z","cycleMs":1,"ok":true,"mode":"5m","signalsCount":0,"cycleProfileMs":{}},{"at":"2026-04-10T13:24:14.230Z","cycleMs":1,"ok":true,"mode":"5m","signalsCount":0,"cycleProfileMs":{}},{"at":"2026-04-10T13:24:15.242Z","cycleMs":1,"ok":true,"mode":"5m","signalsCount":0,"cycleProfileMs":{}},{"at":"2026-04-10T13:24:17.274Z","cycleMs":1,"ok":true,"mode":"5m","signalsCount":0,"cycleProfileMs":{}},{"at":"2026-04-10T13:24:18.289Z","cycleMs":1,"ok":true,"mode":"5m","signalsCount":0,"cycleProfileMs":{}},{"at":"2026-04-10T13:24:20.310Z","cycleMs":1,"ok":true,"mode":"5m","signalsCount":0,"cycleProfileMs":{}},{"at":"2026-04-10T13:24:22.355Z","cycleMs":1,"ok":true,"mode":"5m","signalsCount":0,"cycleProfileMs":{}},{"at":"2026-04-10T13:24:25.399Z","cycleMs":1,"ok":true,"mode":"5m","signalsCount":0,"cycleProfileMs":{}},{"at":"2026-04-10T13:24:27.445Z","cycleMs":1,"ok":true,"mode":"5m","signalsCount":0,"cycleProfileMs":{}},{"at":"2026-04-10T13:24:29.474Z","cycleMs":1,"ok":true,"mode":"5m","signalsCount":0,"cycleProfileMs":{}},{"at":"2026-04-10T13:24:31.513Z","cycleMs":1,"ok":true,"mode":"5m","signalsCount":0,"cycleProfileMs":{}},{"at":"2026-04-10T13:24:33.548Z","cycleMs":1,"ok":true,"mode":"5m","signalsCount":0,"cycleProfileMs":{}},{"at":"2026-04-10T13:24:37.619Z","cycleMs":1,"ok":true,"mode":"5m","signalsCount":0,"cycleProfileMs":{}},{"at":"2026-04-10T13:24:38.646Z","cycleMs":1,"ok":true,"mode":"5m","signalsCount":0,"cycleProfileMs":{}},{"at":"2026-04-10T13:24:41.705Z","cycleMs":1,"ok":true,"mode":"5m","signalsCount":0,"cycleProfileMs":{}},{"at":"2026-04-10T13:24:45.781Z","cycleMs":1,"ok":true,"mode":"5m","signalsCount":0,"cycleProfileMs":{}},{"at":"2026-04-10T13:24:46.800Z","cycleMs":1,"ok":true,"mode":"5m","signalsCount":0,"cycleProfileMs":{}},{"at":"2026-04-10T13:24:48.831Z","cycleMs":1,"ok":true,"mode":"5m","signalsCount":0,"cycleProfileMs":{}},{"at":"2026-04-10T13:24:53.923Z","cycleMs":1,"ok":true,"mode":"5m","signalsCount":0,"cycleProfileMs":{}},{"at":"2026-04-10T13:24:54.938Z","cycleMs":1,"ok":true,"mode":"5m","signalsCount":0,"cycleProfileMs":{}},{"at":"2026-04-10T13:24:56.983Z","cycleMs":1,"ok":true,"mode":"5m","signalsCount":0,"cycleProfileMs":{}},{"at":"2026-04-10T13:24:57.996Z","cycleMs":1,"ok":true,"mode":"5m","signalsCount":0,"cycleProfileMs":{}},{"at":"2026-04-10T13:24:59.020Z","cycleMs":1,"ok":true,"mode":"5m","signalsCount":0,"cycleProfileMs":{}},{"at":"2026-04-10T13:25:05.146Z","cycleMs":1,"ok":true,"mode":"5m","signalsCount":0,"cycleProfileMs":{}},{"at":"2026-04-10T13:25:06.174Z","cycleMs":1,"ok":true,"mode":"5m","signalsCount":0,"cycleProfileMs":{}},{"at":"2026-04-10T13:25:12.257Z","cycleMs":1,"ok":true,"mode":"5m","signalsCount":0,"cycleProfileMs":{}},{"at":"2026-04-10T13:25:17.332Z","cycleMs":1,"ok":true,"mode":"5m","signalsCount":0,"cycleProfileMs":{}},{"at":"2026-04-10T13:25:21.415Z","cycleMs":1,"ok":true,"mode":"5m","signalsCount":0,"cycleProfileMs":{}},{"at":"2026-04-10T13:25:25.487Z","cycleMs":1,"ok":true,"mode":"5m","signalsCount":0,"cycleProfileMs":{}},{"at":"2026-04-10T13:25:29.555Z","cycleMs":1,"ok":true,"mode":"5m","signalsCount":0,"cycleProfileMs":{}},{"at":"2026-04-10T13:25:34.646Z","cycleMs":1,"ok":true,"mode":"5m","signalsCount":0,"cycleProfileMs":{}},{"at":"2026-04-10T13:25:39.747Z","cycleMs":1,"ok":true,"mode":"5m","signalsCount":0,"cycleProfileMs":{}},{"at":"2026-04-10T13:25:40.770Z","cycleMs":1,"ok":true,"mode":"5m","signalsCount":0,"cycleProfileMs":{}},{"at":"2026-04-10T13:25:43.837Z","cycleMs":1,"ok":true,"mode":"5m","signalsCount":0,"cycleProfileMs":{}},{"at":"2026-04-10T13:25:48.903Z","cycleMs":1,"ok":true,"mode":"5m","signalsCount":0,"cycleProfileMs":{}},{"at":"2026-04-10T13:25:49.912Z","cycleMs":1,"ok":true,"mode":"5m","signalsCount":0,"cycleProfileMs":{}},{"at":"2026-04-10T13:25:53.982Z","cycleMs":1,"ok":true,"mode":"5m","signalsCount":0,"cycleProfileMs":{}},{"at":"2026-04-10T13:25:56.022Z","cycleMs":1,"ok":true,"mode":"5m","signalsCount":0,"cycleProfileMs":{}},{"at":"2026-04-10T13:25:57.046Z","cycleMs":1,"ok":true,"mode":"5m","signalsCount":0,"cycleProfileMs":{}},{"at":"2026-04-10T13:25:59.072Z","cycleMs":1,"ok":true,"mode":"5m","signalsCount":0,"cycleProfileMs":{}},{"at":"2026-04-10T13:26:01.103Z","cycleMs":1,"ok":true,"mode":"5m","signalsCount":0,"cycleProfileMs":{}},{"at":"2026-04-10T13:26:03.135Z","cycleMs":1,"ok":true,"mode":"5m","signalsCount":0,"cycleProfileMs":{}},{"at":"2026-04-10T13:26:06.184Z","cycleMs":1,"ok":true,"mode":"5m","signalsCount":0,"cycleProfileMs":{}},{"at":"2026-04-10T13:26:09.241Z","cycleMs":1,"ok":true,"mode":"5m","signalsCount":0,"cycleProfileMs":{}},{"at":"2026-04-10T13:26:10.262Z","cycleMs":1,"ok":true,"mode":"5m","signalsCount":0,"cycleProfileMs":{}},{"at":"2026-04-10T13:26:14.318Z","cycleMs":1,"ok":true,"mode":"5m","signalsCount":0,"cycleProfileMs":{}},{"at":"2026-04-10T13:26:16.344Z","cycleMs":1,"ok":true,"mode":"5m","signalsCount":0,"cycleProfileMs":{}},{"at":"2026-04-10T13:26:18.375Z","cycleMs":1,"ok":true,"mode":"5m","signalsCount":0,"cycleProfileMs":{}},{"at":"2026-04-10T13:26:20.427Z","cycleMs":1,"ok":true,"mode":"5m","signalsCount":0,"cycleProfileMs":{}},{"at":"2026-04-10T13:26:21.454Z","cycleMs":1,"ok":true,"mode":"5m","signalsCount":0,"cycleProfileMs":{}},{"at":"2026-04-10T13:26:22.481Z","cycleMs":1,"ok":true,"mode":"5m","signalsCount":0,"cycleProfileMs":{}},{"at":"2026-04-10T13:26:25.516Z","cycleMs":1,"ok":true,"mode":"5m","signalsCount":0,"cycleProfileMs":{}},{"at":"2026-04-10T13:26:28.566Z","cycleMs":1,"ok":true,"mode":"5m","signalsCount":0,"cycleProfileMs":{}},{"at":"2026-04-10T13:26:31.643Z","cycleMs":1,"ok":true,"mode":"5m","signalsCount":0,"cycleProfileMs":{}},{"at":"2026-04-10T13:26:38.777Z","cycleMs":1,"ok":true,"mode":"5m","signalsCount":0,"cycleProfileMs":{}},{"at":"2026-04-10T13:26:39.797Z","cycleMs":1,"ok":true,"mode":"5m","signalsCount":0,"cycleProfileMs":{}},{"at":"2026-04-10T13:26:41.830Z","cycleMs":1,"ok":true,"mode":"5m","signalsCount":0,"cycleProfileMs":{}},{"at":"2026-04-10T13:26:46.908Z","cycleMs":1,"ok":true,"mode":"5m","signalsCount":0,"cycleProfileMs":{}},{"at":"2026-04-10T13:26:47.931Z","cycleMs":1,"ok":true,"mode":"5m","signalsCount":0,"cycleProfileMs":{}},{"at":"2026-04-10T13:26:49.971Z","cycleMs":1,"ok":true,"mode":"5m","signalsCount":0,"cycleProfileMs":{}},{"at":"2026-04-10T13:26:56.073Z","cycleMs":1,"ok":true,"mode":"5m","signalsCount":0,"cycleProfileMs":{}},{"at":"2026-04-10T13:26:58.106Z","cycleMs":1,"ok":true,"mode":"5m","signalsCount":0,"cycleProfileMs":{}},{"at":"2026-04-10T13:26:59.128Z","cycleMs":1,"ok":true,"mode":"5m","signalsCount":0,"cycleProfileMs":{}},{"at":"2026-04-10T13:27:03.182Z","cycleMs":1,"ok":true,"mode":"5m","signalsCount":0,"cycleProfileMs":{}},{"at":"2026-04-10T13:27:04.206Z","cycleMs":1,"ok":true,"mode":"5m","signalsCount":0,"cycleProfileMs":{}},{"at":"2026-04-10T13:27:05.229Z","cycleMs":1,"ok":true,"mode":"5m","signalsCount":0,"cycleProfileMs":{}},{"at":"2026-04-10T13:27:09.309Z","cycleMs":1,"ok":true,"mode":"5m","signalsCount":0,"cycleProfileMs":{}},{"at":"2026-04-10T13:27:10.334Z","cycleMs":1,"ok":true,"mode":"5m","signalsCount":0,"cycleProfileMs":{}},{"at":"2026-04-10T13:27:13.384Z","cycleMs":1,"ok":true,"mode":"5m","signalsCount":0,"cycleProfileMs":{}},{"at":"2026-04-10T13:27:14.408Z","cycleMs":1,"ok":true,"mode":"5m","signalsCount":0,"cycleProfileMs":{}},{"at":"2026-04-10T13:27:15.430Z","cycleMs":1,"ok":true,"mode":"5m","signalsCount":0,"cycleProfileMs":{}},{"at":"2026-04-10T13:27:16.440Z","cycleMs":1,"ok":true,"mode":"5m","signalsCount":0,"cycleProfileMs":{}},{"at":"2026-04-10T13:27:19.486Z","cycleMs":1,"ok":true,"mode":"5m","signalsCount":0,"cycleProfileMs":{}},{"at":"2026-04-10T13:27:21.510Z","cycleMs":1,"ok":true,"mode":"5m","signalsCount":0,"cycleProfileMs":{}},{"at":"2026-04-10T13:27:27.589Z","cycleMs":1,"ok":true,"mode":"5m","signalsCount":0,"cycleProfileMs":{}},{"at":"2026-04-10T13:27:29.617Z","cycleMs":1,"ok":true,"mode":"5m","signalsCount":0,"cycleProfileMs":{}},{"at":"2026-04-10T13:27:31.641Z","cycleMs":1,"ok":true,"mode":"5m","signalsCount":0,"cycleProfileMs":{}},{"at":"2026-04-10T13:27:32.666Z","cycleMs":1,"ok":true,"mode":"5m","signalsCount":0,"cycleProfileMs":{}},{"at":"2026-04-10T13:27:34.715Z","cycleMs":1,"ok":true,"mode":"5m","signalsCount":0,"cycleProfileMs":{}},{"at":"2026-04-10T13:27:35.734Z","cycleMs":1,"ok":true,"mode":"5m","signalsCount":0,"cycleProfileMs":{}},{"at":"2026-04-10T13:27:39.797Z","cycleMs":1,"ok":true,"mode":"5m","signalsCount":0,"cycleProfileMs":{}},{"at":"2026-04-10T13:27:46.924Z","cycleMs":1,"ok":true,"mode":"5m","signalsCount":0,"cycleProfileMs":{}},{"at":"2026-04-10T13:27:47.948Z","cycleMs":1,"ok":true,"mode":"5m","signalsCount":0,"cycleProfileMs":{}},{"at":"2026-04-10T13:27:50.980Z","cycleMs":1,"ok":true,"mode":"5m","signalsCount":0,"cycleProfileMs":{}},{"at":"2026-04-10T13:27:51.992Z","cycleMs":1,"ok":true,"mode":"5m","signalsCount":0,"cycleProfileMs":{}},{"at":"2026-04-10T13:27:53.007Z","cycleMs":1,"ok":true,"mode":"5m","signalsCount":0,"cycleProfileMs":{}},{"at":"2026-04-10T13:27:57.076Z","cycleMs":1,"ok":true,"mode":"5m","signalsCount":0,"cycleProfileMs":{}},{"at":"2026-04-10T13:28:02.133Z","cycleMs":1,"ok":true,"mode":"5m","signalsCount":0,"cycleProfileMs":{}},{"at":"2026-04-10T13:28:03.149Z","cycleMs":1,"ok":true,"mode":"5m","signalsCount":0,"cycleProfileMs":{}},{"at":"2026-04-10T13:28:05.204Z","cycleMs":1,"ok":true,"mode":"5m","signalsCount":0,"cycleProfileMs":{}},{"at":"2026-04-10T13:28:06.221Z","cycleMs":1,"ok":true,"mode":"5m","signalsCount":0,"cycleProfileMs":{}},{"at":"2026-04-10T13:28:07.243Z","cycleMs":2,"ok":true,"mode":"5m","signalsCount":0,"cycleProfileMs":{}},{"at":"2026-04-10T13:28:08.266Z","cycleMs":1,"ok":true,"mode":"5m","signalsCount":0,"cycleProfileMs":{}},{"at":"2026-04-10T13:28:11.317Z","cycleMs":1,"ok":true,"mode":"5m","signalsCount":0,"cycleProfileMs":{}},{"at":"2026-04-10T13:28:13.360Z","cycleMs":4,"ok":true,"mode":"5m","signalsCount":0,"cycleProfileMs":{}},{"at":"2026-04-10T13:28:15.403Z","cycleMs":1,"ok":true,"mode":"5m","signalsCount":0,"cycleProfileMs":{}},{"at":"2026-04-10T13:28:23.532Z","cycleMs":1,"ok":true,"mode":"5m","signalsCount":0,"cycleProfileMs":{}},{"at":"2026-04-10T13:28:25.579Z","cycleMs":1,"ok":true,"mode":"5m","signalsCount":0,"cycleProfileMs":{}},{"at":"2026-04-10T13:28:27.601Z","cycleMs":1,"ok":true,"mode":"5m","signalsCount":0,"cycleProfileMs":{}},{"at":"2026-04-10T13:28:31.668Z","cycleMs":1,"ok":true,"mode":"5m","signalsCount":0,"cycleProfileMs":{}},{"at":"2026-04-10T13:28:35.743Z","cycleMs":2,"ok":true,"mode":"5m","signalsCount":0,"cycleProfileMs":{}},{"at":"2026-04-10T13:28:37.788Z","cycleMs":1,"ok":true,"mode":"5m","signalsCount":0,"cycleProfileMs":{}},{"at":"2026-04-10T13:28:38.813Z","cycleMs":1,"ok":true,"mode":"5m","signalsCount":0,"cycleProfileMs":{}},{"at":"2026-04-10T13:28:40.842Z","cycleMs":1,"ok":true,"mode":"5m","signalsCount":0,"cycleProfileMs":{}},{"at":"2026-04-10T13:28:43.919Z","cycleMs":1,"ok":true,"mode":"5m","signalsCount":0,"cycleProfileMs":{}},{"at":"2026-04-10T13:28:44.945Z","cycleMs":1,"ok":true,"mode":"5m","signalsCount":0,"cycleProfileMs":{}},{"at":"2026-04-10T13:28:51.048Z","cycleMs":1,"ok":true,"mode":"5m","signalsCount":0,"cycleProfileMs":{}},{"at":"2026-04-10T13:28:52.071Z","cycleMs":1,"ok":true,"mode":"5m","signalsCount":0,"cycleProfileMs":{}},{"at":"2026-04-10T13:28:54.096Z","cycleMs":1,"ok":true,"mode":"5m","signalsCount":0,"cycleProfileMs":{}},{"at":"2026-04-10T13:28:57.155Z","cycleMs":1,"ok":true,"mode":"5m","signalsCount":0,"cycleProfileMs":{}},{"at":"2026-04-10T13:29:01.215Z","cycleMs":1,"ok":true,"mode":"5m","signalsCount":0,"cycleProfileMs":{}},{"at":"2026-04-10T13:29:02.240Z","cycleMs":1,"ok":true,"mode":"5m","signalsCount":0,"cycleProfileMs":{}},{"at":"2026-04-10T13:29:03.262Z","cycleMs":1,"ok":true,"mode":"5m","signalsCount":0,"cycleProfileMs":{}},{"at":"2026-04-10T13:29:04.284Z","cycleMs":1,"ok":true,"mode":"5m","signalsCount":0,"cycleProfileMs":{}},{"at":"2026-04-10T13:29:05.307Z","cycleMs":1,"ok":true,"mode":"5m","signalsCount":0,"cycleProfileMs":{}},{"at":"2026-04-10T13:29:06.322Z","cycleMs":1,"ok":true,"mode":"5m","signalsCount":0,"cycleProfileMs":{}},{"at":"2026-04-10T13:29:12.420Z","cycleMs":1,"ok":true,"mode":"5m","signalsCount":0,"cycleProfileMs":{}},{"at":"2026-04-10T13:29:16.518Z","cycleMs":1,"ok":true,"mode":"5m","signalsCount":0,"cycleProfileMs":{}},{"at":"2026-04-10T13:29:17.546Z","cycleMs":1,"ok":true,"mode":"5m","signalsCount":0,"cycleProfileMs":{}},{"at":"2026-04-10T13:29:20.602Z","cycleMs":1,"ok":true,"mode":"5m","signalsCount":0,"cycleProfileMs":{}},{"at":"2026-04-10T13:29:21.632Z","cycleMs":1,"ok":true,"mode":"5m","signalsCount":0,"cycleProfileMs":{}},{"at":"2026-04-10T13:29:27.734Z","cycleMs":1,"ok":true,"mode":"5m","signalsCount":0,"cycleProfileMs":{}},{"at":"2026-04-10T13:29:28.753Z","cycleMs":1,"ok":true,"mode":"5m","signalsCount":0,"cycleProfileMs":{}},{"at":"2026-04-10T13:29:30.803Z","cycleMs":1,"ok":true,"mode":"5m","signalsCount":0,"cycleProfileMs":{}},{"at":"2026-04-10T13:29:33.867Z","cycleMs":1,"ok":true,"mode":"5m","signalsCount":0,"cycleProfileMs":{}},{"at":"2026-04-10T13:29:35.894Z","cycleMs":1,"ok":true,"mode":"5m","signalsCount":0,"cycleProfileMs":{}},{"at":"2026-04-10T13:29:38.938Z","cycleMs":1,"ok":true,"mode":"5m","signalsCount":0,"cycleProfileMs":{}},{"at":"2026-04-10T13:29:39.965Z","cycleMs":1,"ok":true,"mode":"5m","signalsCount":0,"cycleProfileMs":{}},{"at":"2026-04-10T13:29:40.988Z","cycleMs":1,"ok":true,"mode":"5m","signalsCount":0,"cycleProfileMs":{}},{"at":"2026-04-10T13:29:44.047Z","cycleMs":1,"ok":true,"mode":"5m","signalsCount":0,"cycleProfileMs":{}},{"at":"2026-04-10T13:29:47.101Z","cycleMs":1,"ok":true,"mode":"5m","signalsCount":0,"cycleProfileMs":{}},{"at":"2026-04-10T13:29:48.146Z","cycleMs":1,"ok":true,"mode":"5m","signalsCount":0,"cycleProfileMs":{}},{"at":"2026-04-10T13:29:50.195Z","cycleMs":1,"ok":true,"mode":"5m","signalsCount":0,"cycleProfileMs":{}},{"at":"2026-04-10T13:29:51.217Z","cycleMs":1,"ok":true,"mode":"5m","signalsCount":0,"cycleProfileMs":{}},{"at":"2026-04-10T13:29:53.262Z","cycleMs":1,"ok":true,"mode":"5m","signalsCount":0,"cycleProfileMs":{}},{"at":"2026-04-10T13:29:56.332Z","cycleMs":1,"ok":true,"mode":"5m","signalsCount":0,"cycleProfileMs":{}},{"at":"2026-04-10T13:29:57.346Z","cycleMs":1,"ok":true,"mode":"5m","signalsCount":0,"cycleProfileMs":{}},{"at":"2026-04-10T13:29:59.377Z","cycleMs":1,"ok":true,"mode":"5m","signalsCount":0,"cycleProfileMs":{}},{"at":"2026-04-10T13:30:01.420Z","cycleMs":1,"ok":true,"mode":"5m","signalsCount":0,"cycleProfileMs":{}},{"at":"2026-04-10T13:30:02.456Z","cycleMs":2,"ok":true,"mode":"5m","signalsCount":0,"cycleProfileMs":{}},{"at":"2026-04-10T13:30:03.477Z","cycleMs":1,"ok":true,"mode":"5m","signalsCount":0,"cycleProfileMs":{}},{"at":"2026-04-10T13:30:04.509Z","cycleMs":1,"ok":true,"mode":"5m","signalsCount":0,"cycleProfileMs":{}},{"at":"2026-04-10T13:30:05.531Z","cycleMs":1,"ok":true,"mode":"5m","signalsCount":0,"cycleProfileMs":{}},{"at":"2026-04-10T13:30:10.633Z","cycleMs":1,"ok":true,"mode":"5m","signalsCount":0,"cycleProfileMs":{}},{"at":"2026-04-10T13:30:11.646Z","cycleMs":1,"ok":true,"mode":"5m","signalsCount":0,"cycleProfileMs":{}},{"at":"2026-04-10T13:30:14.707Z","cycleMs":1,"ok":true,"mode":"5m","signalsCount":0,"cycleProfileMs":{}},{"at":"2026-04-10T13:30:15.737Z","cycleMs":1,"ok":true,"mode":"5m","signalsCount":0,"cycleProfileMs":{}},{"at":"2026-04-10T13:30:18.814Z","cycleMs":1,"ok":true,"mode":"5m","signalsCount":0,"cycleProfileMs":{}},{"at":"2026-04-10T13:30:20.866Z","cycleMs":1,"ok":true,"mode":"5m","signalsCount":0,"cycleProfileMs":{}},{"at":"2026-04-10T13:30:22.914Z","cycleMs":1,"ok":true,"mode":"5m","signalsCount":0,"cycleProfileMs":{}},{"at":"2026-04-10T13:30:29.059Z","cycleMs":1,"ok":true,"mode":"5m","signalsCount":0,"cycleProfileMs":{}},{"at":"2026-04-10T13:30:31.098Z","cycleMs":1,"ok":true,"mode":"5m","signalsCount":0,"cycleProfileMs":{}},{"at":"2026-04-10T13:30:32.131Z","cycleMs":1,"ok":true,"mode":"5m","signalsCount":0,"cycleProfileMs":{}},{"at":"2026-04-10T13:30:33.160Z","cycleMs":1,"ok":true,"mode":"5m","signalsCount":0,"cycleProfileMs":{}},{"at":"2026-04-10T13:30:37.221Z","cycleMs":1,"ok":true,"mode":"5m","signalsCount":0,"cycleProfileMs":{}},{"at":"2026-04-10T13:30:42.289Z","cycleMs":1,"ok":true,"mode":"5m","signalsCount":0,"cycleProfileMs":{}},{"at":"2026-04-10T13:30:43.308Z","cycleMs":1,"ok":true,"mode":"5m","signalsCount":0,"cycleProfileMs":{}},{"at":"2026-04-10T13:30:44.344Z","cycleMs":1,"ok":true,"mode":"5m","signalsCount":0,"cycleProfileMs":{}},{"at":"2026-04-10T13:30:49.467Z","cycleMs":1,"ok":true,"mode":"5m","signalsCount":0,"cycleProfileMs":{}},{"at":"2026-04-10T13:30:53.586Z","cycleMs":1,"ok":true,"mode":"5m","signalsCount":0,"cycleProfileMs":{}},{"at":"2026-04-10T13:30:55.640Z","cycleMs":1,"ok":true,"mode":"5m","signalsCount":0,"cycleProfileMs":{}},{"at":"2026-04-10T13:30:56.668Z","cycleMs":1,"ok":true,"mode":"5m","signalsCount":0,"cycleProfileMs":{}},{"at":"2026-04-10T13:30:57.716Z","cycleMs":1,"ok":true,"mode":"5m","signalsCount":0,"cycleProfileMs":{}},{"at":"2026-04-10T13:31:03.864Z","cycleMs":1,"ok":true,"mode":"5m","signalsCount":0,"cycleProfileMs":{}},{"at":"2026-04-10T13:31:04.892Z","cycleMs":1,"ok":true,"mode":"5m","signalsCount":0,"cycleProfileMs":{}},{"at":"2026-04-10T13:31:06.950Z","cycleMs":1,"ok":true,"mode":"5m","signalsCount":0,"cycleProfileMs":{}},{"at":"2026-04-10T13:31:09.011Z","cycleMs":1,"ok":true,"mode":"5m","signalsCount":0,"cycleProfileMs":{}},{"at":"2026-04-10T13:31:11.064Z","cycleMs":1,"ok":true,"mode":"5m","signalsCount":0,"cycleProfileMs":{}},{"at":"2026-04-10T13:31:14.118Z","cycleMs":1,"ok":true,"mode":"5m","signalsCount":0,"cycleProfileMs":{}},{"at":"2026-04-10T13:31:15.139Z","cycleMs":1,"ok":true,"mode":"5m","signalsCount":0,"cycleProfileMs":{}},{"at":"2026-04-10T13:31:16.160Z","cycleMs":1,"ok":true,"mode":"5m","signalsCount":0,"cycleProfileMs":{}},{"at":"2026-04-10T13:31:20.235Z","cycleMs":1,"ok":true,"mode":"5m","signalsCount":0,"cycleProfileMs":{}},{"at":"2026-04-10T13:31:25.309Z","cycleMs":1,"ok":true,"mode":"5m","signalsCount":0,"cycleProfileMs":{}},{"at":"2026-04-10T13:31:31.426Z","cycleMs":1,"ok":true,"mode":"5m","signalsCount":0,"cycleProfileMs":{}},{"at":"2026-04-10T13:31:33.456Z","cycleMs":1,"ok":true,"mode":"5m","signalsCount":0,"cycleProfileMs":{}},{"at":"2026-04-10T13:31:35.494Z","cycleMs":1,"ok":true,"mode":"5m","signalsCount":0,"cycleProfileMs":{}},{"at":"2026-04-10T13:31:36.517Z","cycleMs":1,"ok":true,"mode":"5m","signalsCount":0,"cycleProfileMs":{}},{"at":"2026-04-10T13:31:37.544Z","cycleMs":1,"ok":true,"mode":"5m","signalsCount":0,"cycleProfileMs":{}},{"at":"2026-04-10T13:31:39.576Z","cycleMs":1,"ok":true,"mode":"5m","signalsCount":0,"cycleProfileMs":{}},{"at":"2026-04-10T13:31:40.603Z","cycleMs":1,"ok":true,"mode":"5m","signalsCount":0,"cycleProfileMs":{}},{"at":"2026-04-10T13:31:41.634Z","cycleMs":1,"ok":true,"mode":"5m","signalsCount":0,"cycleProfileMs":{}},{"at":"2026-04-10T13:31:42.661Z","cycleMs":1,"ok":true,"mode":"5m","signalsCount":0,"cycleProfileMs":{}},{"at":"2026-04-10T13:31:44.712Z","cycleMs":1,"ok":true,"mode":"5m","signalsCount":0,"cycleProfileMs":{}},{"at":"2026-04-10T13:31:45.740Z","cycleMs":1,"ok":true,"mode":"5m","signalsCount":0,"cycleProfileMs":{}},{"at":"2026-04-10T13:31:46.799Z","cycleMs":1,"ok":true,"mode":"5m","signalsCount":0,"cycleProfileMs":{}},{"at":"2026-04-10T13:31:48.841Z","cycleMs":1,"ok":true,"mode":"5m","signalsCount":0,"cycleProfileMs":{}},{"at":"2026-04-10T13:31:50.902Z","cycleMs":1,"ok":true,"mode":"5m","signalsCount":0,"cycleProfileMs":{}},{"at":"2026-04-10T13:31:51.922Z","cycleMs":1,"ok":true,"mode":"5m","signalsCount":0,"cycleProfileMs":{}},{"at":"2026-04-10T13:31:55.991Z","cycleMs":1,"ok":true,"mode":"5m","signalsCount":0,"cycleProfileMs":{}},{"at":"2026-04-10T13:31:58.036Z","cycleMs":1,"ok":true,"mode":"5m","signalsCount":0,"cycleProfileMs":{}},{"at":"2026-04-10T13:31:59.061Z","cycleMs":1,"ok":true,"mode":"5m","signalsCount":0,"cycleProfileMs":{}},{"at":"2026-04-10T13:32:00.082Z","cycleMs":1,"ok":true,"mode":"5m","signalsCount":0,"cycleProfileMs":{}},{"at":"2026-04-10T13:32:01.114Z","cycleMs":1,"ok":true,"mode":"5m","signalsCount":0,"cycleProfileMs":{}},{"at":"2026-04-10T13:32:02.148Z","cycleMs":1,"ok":true,"mode":"5m","signalsCount":0,"cycleProfileMs":{}},{"at":"2026-04-10T13:32:03.171Z","cycleMs":1,"ok":true,"mode":"5m","signalsCount":0,"cycleProfileMs":{}},{"at":"2026-04-10T13:32:10.357Z","cycleMs":1,"ok":true,"mode":"5m","signalsCount":0,"cycleProfileMs":{}},{"at":"2026-04-10T13:32:11.377Z","cycleMs":1,"ok":true,"mode":"5m","signalsCount":0,"cycleProfileMs":{}},{"at":"2026-04-10T13:32:13.434Z","cycleMs":1,"ok":true,"mode":"5m","signalsCount":0,"cycleProfileMs":{}},{"at":"2026-04-10T13:32:14.463Z","cycleMs":1,"ok":true,"mode":"5m","signalsCount":0,"cycleProfileMs":{}},{"at":"2026-04-10T13:32:17.549Z","cycleMs":1,"ok":true,"mode":"5m","signalsCount":0,"cycleProfileMs":{}}]