{
  "BTC": [
    {
      "at": 1776122400000,
      "price": 74655.12
    },
    {
      "at": 1776122700000,
      "price": 74650.33
    },
    {
      "at": 1776122700000,
      "price": 74650.33
    },
    {
      "at": 1776123000000,
      "price": 74768.5
    },
    {
      "at": 1776123300000,
      "price": 74826.1
    },
    {
      "at": 1776123600000,
      "price": 74741.28
    },
    {
      "at": 1776123600000,
      "price": 74741.28
    },
    {
      "at": 1776123900000,
      "price": 74605.38
    },
    {
      "at": 1776124200000,
      "price": 74536.86
    },
    {
      "at": 1776124200000,
      "price": 74536.86
    },
    {
      "at": 1776124500000,
      "price": 74611.56
    },
    {
      "at": 1776124800000,
      "price": 74460.72
    },
    {
      "at": 1776125100000,
      "price": 74488.44
    },
    {
      "at": 1776125100000,
      "price": 74488.44
    },
    {
      "at": 1776125400000,
      "price": 74369.07
    },
    {
      "at": 1776125700000,
      "price": 74380.22
    },
    {
      "at": 1776126000000,
      "price": 74439.62
    },
    {
      "at": 1776126300000,
      "price": 74343.42
    },
    {
      "at": 1776126300000,
      "price": 74343.42
    },
    {
      "at": 1776126600000,
      "price": 74306.62
    },
    {
      "at": 1776126900000,
      "price": 74270.82
    },
    {
      "at": 1776126900000,
      "price": 74270.82
    },
    {
      "at": 1776127200000,
      "price": 74432.34
    },
    {
      "at": 1776127500000,
      "price": 74469.53
    },
    {
      "at": 1776127800000,
      "price": 74316.1
    },
    {
      "at": 1776127800000,
      "price": 74316.1
    },
    {
      "at": 1776128100000,
      "price": 74194.21
    },
    {
      "at": 1776128400000,
      "price": 74205.6
    },
    {
      "at": 1776128700000,
      "price": 74211.91
    },
    {
      "at": 1776163800000,
      "price": 74436.78
    },
    {
      "at": 1776163800000,
      "price": 74436.78
    },
    {
      "at": 1776164100000,
      "price": 74403.96
    },
    {
      "at": 1776164100000,
      "price": 74403.96
    },
    {
      "at": 1776164100000,
      "price": 74403.96
    },
    {
      "at": 1776164400000,
      "price": 74384.64
    },
    {
      "at": 1776164400000,
      "price": 74384.64
    },
    {
      "at": 1776164400000,
      "price": 74384.64
    },
    {
      "at": 1776164400000,
      "price": 74384.64
    },
    {
      "at": 1776171600000,
      "price": 74492.51
    },
    {
      "at": 1776171600000,
      "price": 74492.51
    },
    {
      "at": 1776171900000,
      "price": 74635.57
    },
    {
      "at": 1776171900000,
      "price": 74635.57
    },
    {
      "at": 1776172200000,
      "price": 74625.24
    },
    {
      "at": 1776172200000,
      "price": 74625.24
    },
    {
      "at": 1776172500000,
      "price": 74605.44
    },
    {
      "at": 1776172800000,
      "price": 74663.32
    },
    {
      "at": 1776173100000,
      "price": 74752.47
    },
    {
      "at": 1776173400000,
      "price": 74546.01
    },
    {
      "at": 1776173400000,
      "price": 74546.01
    },
    {
      "at": 1776173700000,
      "price": 74777.58
    }
  ]
}