{
  "wsConnected": false,
  "wsLastConnectedAt": null,
  "wsLastBidAskAt": null,
  "lastOrderAt": null,
  "lastOrderSource": null,
  "at": "2026-04-10T12:47:43.907Z",
  "lastRateLimitInfo": {
    "limit": 0,
    "remaining": 0,
    "reset": 0,
    "lastUpdate": 1775825257092
  },
  "status": "online",
  "polymarketDegraded": true,
  "degradedReason": "stop_loss_pass_errors_spike",
  "degradedUntil": "2026-04-10T12:49:43.907Z",
  "parkinsonVol": null,
  "perpSources": {
    "BTC": {
      "pyth": 0,
      "pythTs": 0,
      "lastUpdate": 0
    }
  },
  "assetStates": {},
  "isMaintenance": false,
  "kellyFraction": 0.25,
  "kellyMaxBankrollPct": 0.25,
  "maxConcurrentPositions": 15,
  "availableCapital": null,
  "uptimeStart": 1504.8887263,
  "sniperFilterAudit": {
    "at": null,
    "asset": "BTC",
    "status": "idle",
    "reason": "Initialisé",
    "momentumDelta": 0,
    "isDuplicate": false,
    "isStrong": false,
    "isSignMatch": false
  },
  "latencyHistory": {
    "ws": [],
    "poll": [
      {
        "t": 1775825161950,
        "v": 1
      },
      {
        "t": 1775825162972,
        "v": 0
      },
      {
        "t": 1775825163995,
        "v": 1
      },
      {
        "t": 1775825165029,
        "v": 0
      },
      {
        "t": 1775825166064,
        "v": 1
      },
      {
        "t": 1775825167096,
        "v": 0
      },
      {
        "t": 1775825168107,
        "v": 0
      },
      {
        "t": 1775825169127,
        "v": 0
      },
      {
        "t": 1775825170151,
        "v": 0
      },
      {
        "t": 1775825171169,
        "v": 0
      },
      {
        "t": 1775825172199,
        "v": 0
      },
      {
        "t": 1775825173224,
        "v": 0
      },
      {
        "t": 1775825174246,
        "v": 0
      },
      {
        "t": 1775825175276,
        "v": 0
      },
      {
        "t": 1775825176304,
        "v": 0
      },
      {
        "t": 1775825177313,
        "v": 0
      },
      {
        "t": 1775825178336,
        "v": 1
      },
      {
        "t": 1775825179358,
        "v": 1
      },
      {
        "t": 1775825180389,
        "v": 1
      },
      {
        "t": 1775825181429,
        "v": 1
      },
      {
        "t": 1775825182461,
        "v": 1
      },
      {
        "t": 1775825183489,
        "v": 1
      },
      {
        "t": 1775825184511,
        "v": 0
      },
      {
        "t": 1775825185540,
        "v": 1
      },
      {
        "t": 1775825186570,
        "v": 0
      },
      {
        "t": 1775825187584,
        "v": 0
      },
      {
        "t": 1775825188611,
        "v": 0
      },
      {
        "t": 1775825189623,
        "v": 1
      },
      {
        "t": 1775825190633,
        "v": 1
      },
      {
        "t": 1775825191648,
        "v": 1
      },
      {
        "t": 1775825192662,
        "v": 1
      },
      {
        "t": 1775825193684,
        "v": 0
      },
      {
        "t": 1775825194711,
        "v": 0
      },
      {
        "t": 1775825195733,
        "v": 0
      },
      {
        "t": 1775825196751,
        "v": 0
      },
      {
        "t": 1775825197778,
        "v": 0
      },
      {
        "t": 1775825198793,
        "v": 0
      },
      {
        "t": 1775825199803,
        "v": 1
      },
      {
        "t": 1775825200817,
        "v": 0
      },
      {
        "t": 1775825201842,
        "v": 1
      },
      {
        "t": 1775825202855,
        "v": 0
      },
      {
        "t": 1775825203878,
        "v": 0
      },
      {
        "t": 1775825204904,
        "v": 0
      },
      {
        "t": 1775825205919,
        "v": 0
      },
      {
        "t": 1775825206949,
        "v": 0
      },
      {
        "t": 1775825207976,
        "v": 1
      },
      {
        "t": 1775825208996,
        "v": 0
      },
      {
        "t": 1775825210025,
        "v": 1
      },
      {
        "t": 1775825211062,
        "v": 0
      },
      {
        "t": 1775825212084,
        "v": 0
      },
      {
        "t": 1775825213104,
        "v": 1
      },
      {
        "t": 1775825214131,
        "v": 0
      },
      {
        "t": 1775825215145,
        "v": 0
      },
      {
        "t": 1775825216171,
        "v": 1
      },
      {
        "t": 1775825217194,
        "v": 0
      },
      {
        "t": 1775825218224,
        "v": 1
      },
      {
        "t": 1775825219257,
        "v": 1
      },
      {
        "t": 1775825220280,
        "v": 0
      },
      {
        "t": 1775825221315,
        "v": 1
      },
      {
        "t": 1775825222340,
        "v": 0
      },
      {
        "t": 1775825223366,
        "v": 1
      },
      {
        "t": 1775825224381,
        "v": 0
      },
      {
        "t": 1775825225393,
        "v": 0
      },
      {
        "t": 1775825226416,
        "v": 1
      },
      {
        "t": 1775825227444,
        "v": 0
      },
      {
        "t": 1775825228460,
        "v": 0
      },
      {
        "t": 1775825229480,
        "v": 1
      },
      {
        "t": 1775825230501,
        "v": 1
      },
      {
        "t": 1775825231516,
        "v": 0
      },
      {
        "t": 1775825232541,
        "v": 1
      },
      {
        "t": 1775825233564,
        "v": 1
      },
      {
        "t": 1775825234583,
        "v": 0
      },
      {
        "t": 1775825235614,
        "v": 0
      },
      {
        "t": 1775825236642,
        "v": 0
      },
      {
        "t": 1775825237657,
        "v": 0
      },
      {
        "t": 1775825238681,
        "v": 1
      },
      {
        "t": 1775825239724,
        "v": 1
      },
      {
        "t": 1775825240742,
        "v": 1
      },
      {
        "t": 1775825241770,
        "v": 0
      },
      {
        "t": 1775825242798,
        "v": 1
      },
      {
        "t": 1775825243834,
        "v": 0
      },
      {
        "t": 1775825244859,
        "v": 1
      },
      {
        "t": 1775825245872,
        "v": 1
      },
      {
        "t": 1775825246891,
        "v": 1
      },
      {
        "t": 1775825247914,
        "v": 0
      },
      {
        "t": 1775825248941,
        "v": 0
      },
      {
        "t": 1775825249965,
        "v": 1
      },
      {
        "t": 1775825250993,
        "v": 1
      },
      {
        "t": 1775825252018,
        "v": 0
      },
      {
        "t": 1775825253042,
        "v": 1
      },
      {
        "t": 1775825254062,
        "v": 0
      },
      {
        "t": 1775825255075,
        "v": 0
      },
      {
        "t": 1775825256090,
        "v": 1
      },
      {
        "t": 1775825257115,
        "v": 1
      },
      {
        "t": 1775825258140,
        "v": 0
      },
      {
        "t": 1775825259153,
        "v": 1
      },
      {
        "t": 1775825260180,
        "v": 1
      },
      {
        "t": 1775825261204,
        "v": 0
      },
      {
        "t": 1775825262231,
        "v": 1
      },
      {
        "t": 1775825263268,
        "v": 0
      }
    ]
  },
  "performance": {
    "totalVolume": 0,
    "netProfit": 0,
    "winRatePct": 0,
    "tradeCount": 0,
    "updatedAt": "2026-04-10T12:46:44.059Z"
  },
  "openLimitOrders": 0,
  "executionMode": "LIMIT",
  "rewards": null,
  "trendHistory": [
    {
      "t": "2026-04-10T12:47:43.907Z",
      "vol": 0,
      "rew": 0
    }
  ],
  "equityHistory": [],
  "sniperHUD": {
    "btc": {
      "strike": 0,
      "spot": 0,
      "deltaAbs": 0,
      "deltaPct": 0,
      "upPrice": null,
      "downPrice": null,
      "slotSlug": "Wait...",
      "secondsLeft": 0,
      "isStrikeOfficial": false
    }
  }
}